{
  "Version": 3,
  "Meta": {
    "Duration": 2.833,
    "Fps": 60.0,
    "Loop": true,
    "AreBeziersRestricted": true,
    "FadeInTime": 0.0,
    "FadeOutTime": 0.0,
    "CurveCount": 315,
    "TotalSegmentCount": 540,
    "TotalPointCount": 1609,
    "UserDataCount": 1,
    "TotalUserDataSize": 0
  },
  "Curves": [
    {
      "Target": "Parameter",
      "Id": "man_X2",
      "FadeInTime": -1.0,
      "FadeOutTime": -1.0,
      "Segments": [
        0,
        2.093,
        2,
        0.167,
        2.093,
        1,
        1,
        2.093,
        1.834,
        6.86,
        2.667,
        6.86,
        2,
        2.833,
        6.86
      ]
    },
    {
      "Target": "Parameter",
      "Id": "man_Y2",
      "FadeInTime": -1.0,
      "FadeOutTime": -1.0,
      "Segments": [
        0,
        -0.973,
        2,
        0.167,
        -0.973,
        1,
        1,
        -0.973,
        1.834,
        7.3,
        2.667,
        7.3,
        2,
        2.833,
        7.3
      ]
    },
    {
      "Target": "Parameter",
      "Id": "All_X",
      "FadeInTime": -1.0,
      "FadeOutTime": -1.0,
      "Segments": [
        0,
        0,
        2,
        0.167,
        0,
        1,
        0.411,
        0,
        0.656,
        -0.025,
        0.9,
        -0.08,
        2,
        0.917,
        -0.34,
        1,
        1.5,
        -0.34,
        2.084,
        0,
        2.667,
        0,
        2,
        2.833,
        0
      ]
    },
    {
      "Target": "Parameter",
      "Id": "All_Y",
      "FadeInTime": -1.0,
      "FadeOutTime": -1.0,
      "Segments": [
        0,
        0,
        2,
        0.167,
        0,
        1,
        0.411,
        0,
        0.656,
        0.064,
        0.9,
        0.2,
        2,
        0.917,
        1.38,
        1,
        1.5,
        1.38,
        2.084,
        0.36,
        2.667,
        0.36,
        2,
        2.833,
        0.36
      ]
    },
    {
      "Target": "Parameter",
      "Id": "All_Angle",
      "FadeInTime": -1.0,
      "FadeOutTime": -1.0,
      "Segments": [
        0,
        0,
        2,
        0.167,
        0,
        1,
        0.411,
        -2.333,
        0.656,
        -4.667,
        0.9,
        -7,
        1,
        1.489,
        -4.667,
        2.078,
        -2.333,
        2.667,
        0,
        2,
        2.833,
        0
      ]
    },
    {
      "Target": "Parameter",
      "Id": "All_Size",
      "FadeInTime": -1.0,
      "FadeOutTime": -1.0,
      "Segments": [
        0,
        0,
        2,
        0.167,
        0,
        1,
        0.411,
        0,
        0.656,
        0.788,
        0.9,
        2.47,
        2,
        0.917,
        11.59,
        1,
        1.5,
        11.59,
        2.084,
        4.62,
        2.667,
        4.62,
        2,
        2.833,
        4.62
      ]
    },
    {
      "Target": "Parameter",
      "Id": "Param51",
      "FadeInTime": -1.0,
      "FadeOutTime": -1.0,
      "Segments": [
        0,
        1,
        2,
        0.167,
        1,
        1,
        0.667,
        1,
        1.167,
        -0,
        1.667,
        0,
        2,
        2.667,
        0,
        2,
        2.833,
        0
      ]
    },
    {
      "Target": "Parameter",
      "Id": "ParamAngleX",
      "FadeInTime": -1.0,
      "FadeOutTime": -1.0,
      "Segments": [
        0,
        -6.329,
        2,
        0.167,
        -6.329,
        1,
        0.389,
        -6.329,
        0.611,
        10.178,
        0.833,
        10.178,
        1,
        0.966,
        10.178,
        1.1,
        -11.462,
        1.233,
        -11.462,
        1,
        1.372,
        -11.462,
        1.511,
        1.287,
        1.65,
        5.766,
        1,
        1.767,
        9.528,
        1.883,
        9.182,
        2,
        9.182,
        1,
        2.222,
        9.182,
        2.445,
        -6.329,
        2.667,
        -6.329,
        2,
        2.833,
        -6.329
      ]
    },
    {
      "Target": "Parameter",
      "Id": "ParamAngleY",
      "FadeInTime": -1.0,
      "FadeOutTime": -1.0,
      "Segments": [
        0,
        -9.934,
        2,
        0.167,
        -9.934,
        1,
        0.339,
        -9.934,
        0.511,
        0.856,
        0.683,
        0.856,
        1,
        0.883,
        0.856,
        1.083,
        -11.683,
        1.283,
        -11.683,
        1,
        1.428,
        -11.683,
        1.572,
        4.065,
        1.717,
        4.065,
        1,
        1.872,
        4.065,
        2.028,
        4.395,
        2.183,
        2.656,
        1,
        2.344,
        0.855,
        2.506,
        -17.934,
        2.667,
        -17.934,
        2,
        2.833,
        -17.934
      ]
    },
    {
      "Target": "Parameter",
      "Id": "ParamAngleZ",
      "FadeInTime": -1.0,
      "FadeOutTime": -1.0,
      "Segments": [
        0,
        0.304,
        2,
        0.167,
        0.304,
        1,
        0.367,
        0.304,
        0.567,
        1.425,
        0.767,
        1.425,
        1,
        0.889,
        1.425,
        1.011,
        -1.93,
        1.133,
        -1.93,
        1,
        1.316,
        -1.93,
        1.5,
        1.571,
        1.683,
        1.571,
        1,
        1.761,
        1.571,
        1.839,
        1.131,
        1.917,
        1.131,
        1,
        2.017,
        1.131,
        2.117,
        1.3,
        2.217,
        1.3,
        1,
        2.367,
        1.3,
        2.517,
        0.304,
        2.667,
        0.304,
        2,
        2.833,
        0.304
      ]
    },
    {
      "Target": "Parameter",
      "Id": "ParamNeckZ",
      "FadeInTime": -1.0,
      "FadeOutTime": -1.0,
      "Segments": [
        0,
        -1.654,
        2,
        0.167,
        -1.654,
        1,
        0.345,
        -1.654,
        0.522,
        -0.253,
        0.7,
        -0.253,
        1,
        0.817,
        -0.253,
        0.933,
        -2.741,
        1.05,
        -2.741,
        1,
        1.233,
        -2.741,
        1.417,
        1.647,
        1.6,
        1.647,
        1,
        1.683,
        1.647,
        1.767,
        1.212,
        1.85,
        1.212,
        1,
        1.956,
        1.212,
        2.061,
        1.381,
        2.167,
        1.381,
        1,
        2.334,
        1.381,
        2.5,
        -1.654,
        2.667,
        -1.654,
        2,
        2.833,
        -1.654
      ]
    },
    {
      "Target": "Parameter",
      "Id": "ParamBodyAngleX",
      "FadeInTime": -1.0,
      "FadeOutTime": -1.0,
      "Segments": [
        0,
        -12.491,
        2,
        0.167,
        -12.491,
        1,
        0.411,
        -12.491,
        0.656,
        -9.34,
        0.9,
        -0.144,
        1,
        1.067,
        6.126,
        1.233,
        11.279,
        1.4,
        11.279,
        1,
        1.556,
        11.279,
        1.711,
        10.055,
        1.867,
        10.055,
        1,
        2.134,
        10.055,
        2.4,
        13.189,
        2.667,
        13.189,
        2,
        2.833,
        13.189
      ]
    },
    {
      "Target": "Parameter",
      "Id": "ParamBodyAngleY",
      "FadeInTime": -1.0,
      "FadeOutTime": -1.0,
      "Segments": [
        0,
        0.109,
        2,
        0.167,
        0.109,
        1,
        0.306,
        0.109,
        0.444,
        2.23,
        0.583,
        2.23,
        1,
        0.733,
        2.23,
        0.883,
        -15.856,
        1.033,
        -15.856,
        1,
        1.222,
        -15.856,
        1.411,
        5.132,
        1.6,
        5.132,
        1,
        1.767,
        5.132,
        1.933,
        5.049,
        2.1,
        3.707,
        1,
        2.289,
        2.186,
        2.478,
        0.109,
        2.667,
        0.109,
        2,
        2.833,
        0.109
      ]
    },
    {
      "Target": "Parameter",
      "Id": "ParamBodyAngleY3",
      "FadeInTime": -1.0,
      "FadeOutTime": -1.0,
      "Segments": [
        0,
        -6.009,
        2,
        0.167,
        -6.009,
        1,
        0.311,
        -6.009,
        0.456,
        -0.059,
        0.6,
        -0.059,
        1,
        0.767,
        -0.059,
        0.933,
        -2.145,
        1.1,
        -2.145,
        1,
        1.289,
        -2.145,
        1.478,
        0.24,
        1.667,
        0.24,
        1,
        1.834,
        0.24,
        2,
        0.324,
        2.167,
        -0.081,
        1,
        2.334,
        -0.486,
        2.5,
        -6.009,
        2.667,
        -6.009,
        2,
        2.833,
        -6.009
      ]
    },
    {
      "Target": "Parameter",
      "Id": "ParamShoulderStretch",
      "FadeInTime": -1.0,
      "FadeOutTime": -1.0,
      "Segments": [
        0,
        -4.574,
        2,
        0.167,
        -4.574,
        1,
        0.428,
        -4.574,
        0.689,
        3.817,
        0.95,
        3.817,
        1,
        1.161,
        3.817,
        1.372,
        -3.207,
        1.583,
        -3.207,
        1,
        1.739,
        -3.207,
        1.894,
        -2.145,
        2.05,
        -2.145,
        1,
        2.256,
        -2.145,
        2.461,
        -4.258,
        2.667,
        -4.258,
        2,
        2.833,
        -4.258
      ]
    },
    {
      "Target": "Parameter",
      "Id": "ParamShoulderStretch2",
      "FadeInTime": -1.0,
      "FadeOutTime": -1.0,
      "Segments": [
        0,
        -10.312,
        2,
        0.167,
        -10.312,
        1,
        0.428,
        -10.312,
        0.689,
        2.248,
        0.95,
        2.248,
        1,
        1.161,
        2.248,
        1.372,
        -4.017,
        1.583,
        -4.017,
        1,
        1.739,
        -4.017,
        1.894,
        -3.033,
        2.05,
        -3.033,
        1,
        2.256,
        -3.033,
        2.461,
        -8.46,
        2.667,
        -8.46,
        2,
        2.833,
        -8.46
      ]
    },
    {
      "Target": "Parameter",
      "Id": "ParamChestZ3",
      "FadeInTime": -1.0,
      "FadeOutTime": -1.0,
      "Segments": [
        0,
        -1.975,
        2,
        0.167,
        -1.975,
        1,
        0.45,
        -1.975,
        0.734,
        -1.978,
        1.017,
        -1.93,
        1,
        1.189,
        -1.901,
        1.361,
        1.034,
        1.533,
        1.034,
        1,
        1.716,
        1.034,
        1.9,
        1.078,
        2.083,
        0.888,
        1,
        2.278,
        0.687,
        2.472,
        -1.975,
        2.667,
        -1.975,
        2,
        2.833,
        -1.975
      ]
    },
    {
      "Target": "Parameter",
      "Id": "ParamWaistZ3",
      "FadeInTime": -1.0,
      "FadeOutTime": -1.0,
      "Segments": [
        0,
        -1.543,
        2,
        0.167,
        -1.543,
        1,
        0.422,
        -1.543,
        0.678,
        -1.933,
        0.933,
        -1.933,
        1,
        1.105,
        -1.933,
        1.278,
        1.111,
        1.45,
        1.111,
        1,
        1.633,
        1.111,
        1.817,
        1.163,
        2,
        0.965,
        1,
        2.222,
        0.725,
        2.445,
        -1.543,
        2.667,
        -1.543,
        2,
        2.833,
        -1.543
      ]
    },
    {
      "Target": "Parameter",
      "Id": "ParamButtZ4",
      "FadeInTime": -1.0,
      "FadeOutTime": -1.0,
      "Segments": [
        0,
        -0.911,
        2,
        0.167,
        -0.911,
        1,
        0.4,
        -0.911,
        0.634,
        -1.932,
        0.867,
        -1.932,
        1,
        1.039,
        -1.932,
        1.211,
        1.175,
        1.383,
        1.175,
        1,
        1.566,
        1.175,
        1.75,
        1.229,
        1.933,
        1.029,
        1,
        2.178,
        0.762,
        2.422,
        -0.911,
        2.667,
        -0.911,
        2,
        2.833,
        -0.911
      ]
    },
    {
      "Target": "Parameter",
      "Id": "Param32",
      "FadeInTime": -1.0,
      "FadeOutTime": -1.0,
      "Segments": [
        0,
        0,
        2,
        0.167,
        0,
        2,
        2.167,
        0,
        1,
        2.334,
        0,
        2.5,
        1,
        2.667,
        1,
        2,
        2.833,
        1
      ]
    },
    {
      "Target": "Parameter",
      "Id": "Param28",
      "FadeInTime": -1.0,
      "FadeOutTime": -1.0,
      "Segments": [
        0,
        0,
        2,
        0.167,
        0,
        1,
        1,
        0,
        1.834,
        0.5,
        2.667,
        0.5,
        2,
        2.833,
        0.5
      ]
    },
    {
      "Target": "Parameter",
      "Id": "Param126",
      "FadeInTime": -1.0,
      "FadeOutTime": -1.0,
      "Segments": [
        0,
        0,
        2,
        0.167,
        0,
        1,
        1,
        0,
        1.834,
        -1.986,
        2.667,
        -1.986,
        2,
        2.833,
        -1.986
      ]
    },
    {
      "Target": "Parameter",
      "Id": "Param142",
      "FadeInTime": -1.0,
      "FadeOutTime": -1.0,
      "Segments": [
        0,
        0,
        2,
        0.167,
        0,
        1,
        1,
        0,
        1.834,
        4.797,
        2.667,
        4.797,
        2,
        2.833,
        4.797
      ]
    },
    {
      "Target": "Parameter",
      "Id": "Param44",
      "FadeInTime": -1.0,
      "FadeOutTime": -1.0,
      "Segments": [
        0,
        15,
        2,
        0.167,
        15,
        2,
        0.75,
        15,
        2,
        0.767,
        23.82,
        2,
        1.117,
        23.82,
        1,
        1.122,
        23.82,
        1.128,
        30,
        1.133,
        30,
        2,
        2.667,
        30,
        2,
        2.833,
        30
      ]
    },
    {
      "Target": "Parameter",
      "Id": "ParamForearmRChange",
      "FadeInTime": -1.0,
      "FadeOutTime": -1.0,
      "Segments": [
        0,
        -20,
        2,
        0.167,
        -20,
        1,
        0.334,
        -20,
        0.5,
        -30,
        0.667,
        -30,
        1,
        0.822,
        -30,
        0.978,
        12.357,
        1.133,
        12.357,
        1,
        1.644,
        12.357,
        2.156,
        -10.4,
        2.667,
        -10.4,
        2,
        2.833,
        -10.4
      ]
    },
    {
      "Target": "Parameter",
      "Id": "ParamHandRStretch",
      "FadeInTime": -1.0,
      "FadeOutTime": -1.0,
      "Segments": [
        0,
        0,
        2,
        0.167,
        0,
        1,
        1,
        0,
        1.834,
        5.6,
        2.667,
        5.6,
        2,
        2.833,
        5.6
      ]
    },
    {
      "Target": "Parameter",
      "Id": "ParamArmRAngle",
      "FadeInTime": -1.0,
      "FadeOutTime": -1.0,
      "Segments": [
        0,
        1.58,
        2,
        0.167,
        1.58,
        2,
        0.517,
        1.58,
        1,
        0.672,
        1.58,
        0.828,
        2.593,
        0.983,
        2.593,
        1,
        1.322,
        2.593,
        1.661,
        -1.057,
        2,
        -1.057,
        1,
        2.222,
        -1.057,
        2.445,
        -1.055,
        2.667,
        -1.055,
        2,
        2.833,
        -1.055
      ]
    },
    {
      "Target": "Parameter",
      "Id": "ParamForearmRAngle",
      "FadeInTime": -1.0,
      "FadeOutTime": -1.0,
      "Segments": [
        0,
        2.395,
        2,
        0.167,
        2.395,
        1,
        0.334,
        2.395,
        0.5,
        2.755,
        0.667,
        2.755,
        1,
        0.822,
        2.755,
        0.978,
        1.062,
        1.133,
        1.062,
        1,
        1.422,
        1.062,
        1.711,
        12.851,
        2,
        12.851,
        1,
        2.222,
        12.851,
        2.445,
        11.673,
        2.667,
        11.673,
        2,
        2.833,
        11.673
      ]
    },
    {
      "Target": "Parameter",
      "Id": "ParamHandRAngle",
      "FadeInTime": -1.0,
      "FadeOutTime": -1.0,
      "Segments": [
        0,
        11,
        2,
        0.167,
        11,
        1,
        0.361,
        11,
        0.556,
        16,
        0.75,
        16,
        1,
        0.906,
        16,
        1.061,
        -17.729,
        1.217,
        -17.729,
        1,
        1.7,
        -17.729,
        2.184,
        15.719,
        2.667,
        15.719,
        2,
        2.833,
        15.719
      ]
    },
    {
      "Target": "Parameter",
      "Id": "Param5",
      "FadeInTime": -1.0,
      "FadeOutTime": -1.0,
      "Segments": [
        0,
        -20,
        2,
        0.167,
        -20,
        1,
        1,
        -20,
        1.834,
        4,
        2.667,
        4,
        2,
        2.833,
        4
      ]
    },
    {
      "Target": "Parameter",
      "Id": "ParamHandRREDisplay",
      "FadeInTime": -1.0,
      "FadeOutTime": -1.0,
      "Segments": [
        0,
        10,
        2,
        0.167,
        10,
        2,
        0.9,
        10,
        2,
        0.917,
        19,
        2,
        2.667,
        19,
        2,
        2.833,
        19
      ]
    },
    {
      "Target": "Parameter",
      "Id": "ParamHandRAnimation",
      "FadeInTime": -1.0,
      "FadeOutTime": -1.0,
      "Segments": [
        0,
        0,
        2,
        0.167,
        0,
        1,
        1,
        0,
        1.834,
        -30,
        2.667,
        -30,
        2,
        2.833,
        -30
      ]
    },
    {
      "Target": "Parameter",
      "Id": "ParamArmRStretch2",
      "FadeInTime": -1.0,
      "FadeOutTime": -1.0,
      "Segments": [
        0,
        -17.301,
        2,
        0.167,
        -17.301,
        1,
        1,
        -17.301,
        1.834,
        -18.387,
        2.667,
        -18.387,
        2,
        2.833,
        -18.387
      ]
    },
    {
      "Target": "Parameter",
      "Id": "ParamHandRStretch2",
      "FadeInTime": -1.0,
      "FadeOutTime": -1.0,
      "Segments": [
        0,
        -17.538,
        2,
        0.167,
        -17.538,
        1,
        1,
        -17.538,
        1.834,
        -18.571,
        2.667,
        -18.571,
        2,
        2.833,
        -18.571
      ]
    },
    {
      "Target": "Parameter",
      "Id": "ParamArmRAngle2",
      "FadeInTime": -1.0,
      "FadeOutTime": -1.0,
      "Segments": [
        0,
        -2.344,
        2,
        0.167,
        -2.344,
        1,
        1,
        -2.344,
        1.834,
        -1.998,
        2.667,
        -1.998,
        2,
        2.833,
        -1.998
      ]
    },
    {
      "Target": "Parameter",
      "Id": "ParamForearmRAngle2",
      "FadeInTime": -1.0,
      "FadeOutTime": -1.0,
      "Segments": [
        0,
        28.698,
        2,
        0.167,
        28.698,
        1,
        1,
        28.698,
        1.834,
        29.616,
        2.667,
        29.616,
        2,
        2.833,
        29.616
      ]
    },
    {
      "Target": "Parameter",
      "Id": "ParamHandRAngle2",
      "FadeInTime": -1.0,
      "FadeOutTime": -1.0,
      "Segments": [
        0,
        5.004,
        2,
        0.167,
        5.004,
        1,
        1,
        5.004,
        1.834,
        4.282,
        2.667,
        4.282,
        2,
        2.833,
        4.282
      ]
    },
    {
      "Target": "Parameter",
      "Id": "Param43",
      "FadeInTime": -1.0,
      "FadeOutTime": -1.0,
      "Segments": [
        0,
        0.434,
        2,
        0.167,
        0.434,
        1,
        1,
        0.434,
        1.834,
        0.433,
        2.667,
        0.433,
        2,
        2.833,
        0.433
      ]
    },
    {
      "Target": "Parameter",
      "Id": "Param134",
      "FadeInTime": -1.0,
      "FadeOutTime": -1.0,
      "Segments": [
        0,
        -24.784,
        2,
        0.167,
        -24.784,
        1,
        1,
        -24.784,
        1.834,
        -24.788,
        2.667,
        -24.788,
        2,
        2.833,
        -24.788
      ]
    },
    {
      "Target": "Parameter",
      "Id": "Param130",
      "FadeInTime": -1.0,
      "FadeOutTime": -1.0,
      "Segments": [
        0,
        -27.052,
        2,
        0.167,
        -27.052,
        1,
        1,
        -27.052,
        1.834,
        -27.05,
        2.667,
        -27.05,
        2,
        2.833,
        -27.05
      ]
    },
    {
      "Target": "Parameter",
      "Id": "ParamEyeLOpen",
      "FadeInTime": -1.0,
      "FadeOutTime": -1.0,
      "Segments": [
        0,
        1,
        2,
        0.167,
        1,
        2,
        0.85,
        1,
        1,
        0.933,
        1,
        1.017,
        0,
        1.1,
        0,
        1,
        1.172,
        0,
        1.245,
        1,
        1.317,
        1,
        2,
        2.667,
        1,
        2,
        2.833,
        1
      ]
    },
    {
      "Target": "Parameter",
      "Id": "ParamEyeROpen",
      "FadeInTime": -1.0,
      "FadeOutTime": -1.0,
      "Segments": [
        0,
        1,
        2,
        0.167,
        1,
        2,
        0.85,
        1,
        1,
        0.933,
        1,
        1.017,
        0,
        1.1,
        0,
        1,
        1.172,
        0,
        1.245,
        1,
        1.317,
        1,
        2,
        2.667,
        1,
        2,
        2.833,
        1
      ]
    },
    {
      "Target": "Parameter",
      "Id": "ParamMouthForm",
      "FadeInTime": -1.0,
      "FadeOutTime": -1.0,
      "Segments": [
        0,
        0.4,
        2,
        0.167,
        0.4,
        1,
        0.539,
        0.4,
        0.911,
        0.097,
        1.283,
        -0.4,
        1,
        1.455,
        -0.63,
        1.628,
        -0.7,
        1.8,
        -0.7,
        1,
        2.089,
        -0.7,
        2.378,
        0.4,
        2.667,
        0.4,
        2,
        2.833,
        0.4
      ]
    },
    {
      "Target": "Parameter",
      "Id": "ParamMouthOpenY",
      "FadeInTime": -1.0,
      "FadeOutTime": -1.0,
      "Segments": [
        0,
        0.419,
        2,
        0.167,
        0.419,
        1,
        0.539,
        0.419,
        0.911,
        0.373,
        1.283,
        0.2,
        1,
        1.455,
        0.12,
        1.628,
        0,
        1.8,
        0,
        1,
        2.089,
        0,
        2.378,
        0.419,
        2.667,
        0.419,
        2,
        2.833,
        0.419
      ]
    },
    {
      "Target": "Parameter",
      "Id": "MB_wutixialuojiaodu",
      "FadeInTime": -1.0,
      "FadeOutTime": -1.0,
      "Segments": [
        0,
        -7.878,
        2,
        0.167,
        -7.878,
        1,
        1,
        -7.878,
        1.834,
        0,
        2.667,
        0,
        2,
        2.833,
        0
      ]
    },
    {
      "Target": "Parameter",
      "Id": "MB_Awutidaxiao",
      "FadeInTime": -1.0,
      "FadeOutTime": -1.0,
      "Segments": [
        0,
        -0.376,
        2,
        0.167,
        -0.376,
        1,
        1,
        -0.376,
        1.834,
        -0.6,
        2.667,
        -0.6,
        2,
        2.833,
        -0.6
      ]
    },
    {
      "Target": "Parameter",
      "Id": "MB_Awutijiaodu",
      "FadeInTime": -1.0,
      "FadeOutTime": -1.0,
      "Segments": [
        0,
        0.695,
        2,
        0.167,
        0.695,
        1,
        1,
        0.695,
        1.834,
        0.8,
        2.667,
        0.8,
        2,
        2.833,
        0.8
      ]
    },
    {
      "Target": "Parameter",
      "Id": "MB_Cwutidaxiao",
      "FadeInTime": -1.0,
      "FadeOutTime": -1.0,
      "Segments": [
        0,
        -0.065,
        2,
        0.167,
        -0.065,
        1,
        1,
        -0.065,
        1.834,
        -0.493,
        2.667,
        -0.493,
        2,
        2.833,
        -0.493
      ]
    },
    {
      "Target": "Parameter",
      "Id": "MB_Cwutijiaodu",
      "FadeInTime": -1.0,
      "FadeOutTime": -1.0,
      "Segments": [
        0,
        -0.906,
        2,
        0.167,
        -0.906,
        1,
        1,
        -0.906,
        1.834,
        -0.9,
        2.667,
        -0.9,
        2,
        2.833,
        -0.9
      ]
    },
    {
      "Target": "Parameter",
      "Id": "MB_Cwutifanzhuan",
      "FadeInTime": -1.0,
      "FadeOutTime": -1.0,
      "Segments": [
        0,
        -0.983,
        2,
        0.167,
        -0.983,
        1,
        1,
        -0.983,
        1.834,
        -0.7,
        2.667,
        -0.7,
        2,
        2.833,
        -0.7
      ]
    },
    {
      "Target": "Parameter",
      "Id": "MB_Bwutidaxiao",
      "FadeInTime": -1.0,
      "FadeOutTime": -1.0,
      "Segments": [
        0,
        0.171,
        2,
        0.167,
        0.171,
        1,
        1,
        0.171,
        1.834,
        -0.322,
        2.667,
        -0.322,
        2,
        2.833,
        -0.322
      ]
    },
    {
      "Target": "Parameter",
      "Id": "MB_Bwutijiaodu",
      "FadeInTime": -1.0,
      "FadeOutTime": -1.0,
      "Segments": [
        0,
        -0.718,
        2,
        0.167,
        -0.718,
        1,
        1,
        -0.718,
        1.834,
        -0.7,
        2.667,
        -0.7,
        2,
        2.833,
        -0.7
      ]
    },
    {
      "Target": "Parameter",
      "Id": "MB_Bwutifanzhuan",
      "FadeInTime": -1.0,
      "FadeOutTime": -1.0,
      "Segments": [
        0,
        0.265,
        2,
        0.167,
        0.265,
        1,
        1,
        0.265,
        1.834,
        -0.3,
        2.667,
        -0.3,
        2,
        2.833,
        -0.3
      ]
    },
    {
      "Target": "Parameter",
      "Id": "MB_wutixialuoxunhuan",
      "FadeInTime": -1.0,
      "FadeOutTime": -1.0,
      "Segments": [
        0,
        1.601,
        2,
        0.167,
        1.601,
        1,
        1,
        1.067,
        1.834,
        0.534,
        2.667,
        0,
        2,
        2.833,
        0
      ]
    },
    {
      "Target": "Parameter",
      "Id": "GL1",
      "FadeInTime": -1.0,
      "FadeOutTime": -1.0,
      "Segments": [
        0,
        0.534,
        2,
        0.167,
        0.534,
        1,
        1,
        0.356,
        1.834,
        0.178,
        2.667,
        0,
        2,
        2.833,
        0
      ]
    },
    {
      "Target": "Parameter",
      "Id": "GL2",
      "FadeInTime": -1.0,
      "FadeOutTime": -1.0,
      "Segments": [
        0,
        0.924,
        2,
        0.167,
        0.924,
        1,
        1,
        0.746,
        1.834,
        0.568,
        2.667,
        0.39,
        2,
        2.833,
        0.39
      ]
    },
    {
      "Target": "Parameter",
      "Id": "GL3",
      "FadeInTime": -1.0,
      "FadeOutTime": -1.0,
      "Segments": [
        0,
        1.254,
        2,
        0.167,
        1.254,
        1,
        1,
        1.076,
        1.834,
        0.898,
        2.667,
        0.72,
        2,
        2.833,
        0.72
      ]
    },
    {
      "Target": "Parameter",
      "Id": "GL4",
      "FadeInTime": -1.0,
      "FadeOutTime": -1.0,
      "Segments": [
        0,
        0.744,
        2,
        0.167,
        0.744,
        1,
        1,
        0.566,
        1.834,
        0.388,
        2.667,
        0.21,
        2,
        2.833,
        0.21
      ]
    },
    {
      "Target": "Parameter",
      "Id": "GL5",
      "FadeInTime": -1.0,
      "FadeOutTime": -1.0,
      "Segments": [
        0,
        1.064,
        2,
        0.167,
        1.064,
        1,
        1,
        0.886,
        1.834,
        0.708,
        2.667,
        0.53,
        2,
        2.833,
        0.53
      ]
    },
    {
      "Target": "Parameter",
      "Id": "GL6",
      "FadeInTime": -1.0,
      "FadeOutTime": -1.0,
      "Segments": [
        0,
        1.424,
        2,
        0.167,
        1.424,
        1,
        1,
        1.246,
        1.834,
        1.068,
        2.667,
        0.89,
        2,
        2.833,
        0.89
      ]
    },
    {
      "Target": "Parameter",
      "Id": "GL7",
      "FadeInTime": -1.0,
      "FadeOutTime": -1.0,
      "Segments": [
        0,
        1.304,
        2,
        0.167,
        1.304,
        1,
        1,
        1.126,
        1.834,
        0.948,
        2.667,
        0.77,
        2,
        2.833,
        0.77
      ]
    },
    {
      "Target": "Parameter",
      "Id": "GL8",
      "FadeInTime": -1.0,
      "FadeOutTime": -1.0,
      "Segments": [
        0,
        0.624,
        2,
        0.167,
        0.624,
        1,
        1,
        0.446,
        1.834,
        0.268,
        2.667,
        0.09,
        2,
        2.833,
        0.09
      ]
    },
    {
      "Target": "Parameter",
      "Id": "GL9",
      "FadeInTime": -1.0,
      "FadeOutTime": -1.0,
      "Segments": [
        0,
        0.835,
        2,
        0.167,
        0.835,
        1,
        1,
        0.657,
        1.834,
        0.479,
        2.667,
        0.301,
        2,
        2.833,
        0.301
      ]
    },
    {
      "Target": "Parameter",
      "Id": "GL10",
      "FadeInTime": -1.0,
      "FadeOutTime": -1.0,
      "Segments": [
        0,
        0.984,
        2,
        0.167,
        0.984,
        1,
        1,
        0.806,
        1.834,
        0.628,
        2.667,
        0.45,
        2,
        2.833,
        0.45
      ]
    },
    {
      "Target": "Parameter",
      "Id": "GL11",
      "FadeInTime": -1.0,
      "FadeOutTime": -1.0,
      "Segments": [
        0,
        1.174,
        2,
        0.167,
        1.174,
        1,
        1,
        0.996,
        1.834,
        0.818,
        2.667,
        0.64,
        2,
        2.833,
        0.64
      ]
    },
    {
      "Target": "Parameter",
      "Id": "GL12",
      "FadeInTime": -1.0,
      "FadeOutTime": -1.0,
      "Segments": [
        0,
        0.684,
        2,
        0.167,
        0.684,
        1,
        1,
        0.506,
        1.834,
        0.328,
        2.667,
        0.15,
        2,
        2.833,
        0.15
      ]
    },
    {
      "Target": "Parameter",
      "Id": "GL13",
      "FadeInTime": -1.0,
      "FadeOutTime": -1.0,
      "Segments": [
        0,
        1.119,
        2,
        0.167,
        1.119,
        1,
        1,
        0.941,
        1.834,
        0.763,
        2.667,
        0.585,
        2,
        2.833,
        0.585
      ]
    },
    {
      "Target": "Parameter",
      "Id": "GL14",
      "FadeInTime": -1.0,
      "FadeOutTime": -1.0,
      "Segments": [
        0,
        0.534,
        2,
        0.167,
        0.534,
        1,
        1,
        0.356,
        1.834,
        0.178,
        2.667,
        0,
        2,
        2.833,
        0
      ]
    },
    {
      "Target": "Parameter",
      "Id": "Param161",
      "FadeInTime": -1.0,
      "FadeOutTime": -1.0,
      "Segments": [
        0,
        0.844,
        2,
        0.167,
        0.844,
        1,
        1,
        0.733,
        1.834,
        0.621,
        2.667,
        0.51,
        2,
        2.833,
        0.51
      ]
    },
    {
      "Target": "Parameter",
      "Id": "Param162",
      "FadeInTime": -1.0,
      "FadeOutTime": -1.0,
      "Segments": [
        0,
        0.644,
        2,
        0.167,
        0.644,
        1,
        1,
        0.533,
        1.834,
        0.421,
        2.667,
        0.31,
        2,
        2.833,
        0.31
      ]
    },
    {
      "Target": "Parameter",
      "Id": "Param163",
      "FadeInTime": -1.0,
      "FadeOutTime": -1.0,
      "Segments": [
        0,
        1.054,
        2,
        0.167,
        1.054,
        1,
        1,
        0.943,
        1.834,
        0.831,
        2.667,
        0.72,
        2,
        2.833,
        0.72
      ]
    },
    {
      "Target": "Parameter",
      "Id": "Param164",
      "FadeInTime": -1.0,
      "FadeOutTime": -1.0,
      "Segments": [
        0,
        0.334,
        2,
        0.167,
        0.334,
        1,
        1,
        0.223,
        1.834,
        0.111,
        2.667,
        0,
        2,
        2.833,
        0
      ]
    },
    {
      "Target": "Parameter",
      "Id": "Param165",
      "FadeInTime": -1.0,
      "FadeOutTime": -1.0,
      "Segments": [
        0,
        0.504,
        2,
        0.167,
        0.504,
        1,
        1,
        0.393,
        1.834,
        0.281,
        2.667,
        0.17,
        2,
        2.833,
        0.17
      ]
    },
    {
      "Target": "Parameter",
      "Id": "Param75",
      "FadeInTime": -1.0,
      "FadeOutTime": -1.0,
      "Segments": [
        0,
        1,
        1,
        0.944,
        1,
        1.889,
        1,
        2.833,
        1
      ]
    },
    {
      "Target": "Parameter",
      "Id": "K1",
      "FadeInTime": -1.0,
      "FadeOutTime": -1.0,
      "Segments": [
        0,
        0,
        1,
        0.944,
        0,
        1.889,
        0,
        2.833,
        0
      ]
    },
    {
      "Target": "Parameter",
      "Id": "K2",
      "FadeInTime": -1.0,
      "FadeOutTime": -1.0,
      "Segments": [
        0,
        0,
        1,
        0.944,
        0,
        1.889,
        0,
        2.833,
        0
      ]
    },
    {
      "Target": "Parameter",
      "Id": "K3",
      "FadeInTime": -1.0,
      "FadeOutTime": -1.0,
      "Segments": [
        0,
        0,
        1,
        0.944,
        0,
        1.889,
        0,
        2.833,
        0
      ]
    },
    {
      "Target": "Parameter",
      "Id": "man_X",
      "FadeInTime": -1.0,
      "FadeOutTime": -1.0,
      "Segments": [
        0,
        0,
        1,
        0.944,
        0,
        1.889,
        0,
        2.833,
        0
      ]
    },
    {
      "Target": "Parameter",
      "Id": "man_Y",
      "FadeInTime": -1.0,
      "FadeOutTime": -1.0,
      "Segments": [
        0,
        0,
        1,
        0.944,
        0,
        1.889,
        0,
        2.833,
        0
      ]
    },
    {
      "Target": "Parameter",
      "Id": "man_Angle",
      "FadeInTime": -1.0,
      "FadeOutTime": -1.0,
      "Segments": [
        0,
        0,
        1,
        0.944,
        0,
        1.889,
        0,
        2.833,
        0
      ]
    },
    {
      "Target": "Parameter",
      "Id": "man_Size",
      "FadeInTime": -1.0,
      "FadeOutTime": -1.0,
      "Segments": [
        0,
        0,
        1,
        0.944,
        0,
        1.889,
        0,
        2.833,
        0
      ]
    },
    {
      "Target": "Parameter",
      "Id": "Param45",
      "FadeInTime": -1.0,
      "FadeOutTime": -1.0,
      "Segments": [
        0,
        0,
        1,
        0.944,
        0,
        1.889,
        0,
        2.833,
        0
      ]
    },
    {
      "Target": "Parameter",
      "Id": "Param46",
      "FadeInTime": -1.0,
      "FadeOutTime": -1.0,
      "Segments": [
        0,
        0,
        1,
        0.944,
        0,
        1.889,
        0,
        2.833,
        0
      ]
    },
    {
      "Target": "Parameter",
      "Id": "Param214",
      "FadeInTime": -1.0,
      "FadeOutTime": -1.0,
      "Segments": [
        0,
        0,
        1,
        0.944,
        0,
        1.889,
        0,
        2.833,
        0
      ]
    },
    {
      "Target": "Parameter",
      "Id": "shangguang2",
      "FadeInTime": -1.0,
      "FadeOutTime": -1.0,
      "Segments": [
        0,
        0,
        1,
        0.944,
        0,
        1.889,
        0,
        2.833,
        0
      ]
    },
    {
      "Target": "Parameter",
      "Id": "Param189",
      "FadeInTime": -1.0,
      "FadeOutTime": -1.0,
      "Segments": [
        0,
        0,
        1,
        0.944,
        0,
        1.889,
        0,
        2.833,
        0
      ]
    },
    {
      "Target": "Parameter",
      "Id": "shangguang",
      "FadeInTime": -1.0,
      "FadeOutTime": -1.0,
      "Segments": [
        0,
        0,
        1,
        0.944,
        0,
        1.889,
        0,
        2.833,
        0
      ]
    },
    {
      "Target": "Parameter",
      "Id": "Param64",
      "FadeInTime": -1.0,
      "FadeOutTime": -1.0,
      "Segments": [
        0,
        0,
        1,
        0.944,
        0,
        1.889,
        0,
        2.833,
        0
      ]
    },
    {
      "Target": "Parameter",
      "Id": "Param12",
      "FadeInTime": -1.0,
      "FadeOutTime": -1.0,
      "Segments": [
        0,
        0,
        1,
        0.944,
        0,
        1.889,
        0,
        2.833,
        0
      ]
    },
    {
      "Target": "Parameter",
      "Id": "Param103",
      "FadeInTime": -1.0,
      "FadeOutTime": -1.0,
      "Segments": [
        0,
        0,
        1,
        0.944,
        0,
        1.889,
        0,
        2.833,
        0
      ]
    },
    {
      "Target": "Parameter",
      "Id": "Param104",
      "FadeInTime": -1.0,
      "FadeOutTime": -1.0,
      "Segments": [
        0,
        0,
        1,
        0.944,
        0,
        1.889,
        0,
        2.833,
        0
      ]
    },
    {
      "Target": "Parameter",
      "Id": "Param105",
      "FadeInTime": -1.0,
      "FadeOutTime": -1.0,
      "Segments": [
        0,
        0,
        1,
        0.944,
        0,
        1.889,
        0,
        2.833,
        0
      ]
    },
    {
      "Target": "Parameter",
      "Id": "MB_xingfengTMD",
      "FadeInTime": -1.0,
      "FadeOutTime": -1.0,
      "Segments": [
        0,
        0,
        1,
        0.944,
        0,
        1.889,
        0,
        2.833,
        0
      ]
    },
    {
      "Target": "Parameter",
      "Id": "MB_xingfengyaobai",
      "FadeInTime": -1.0,
      "FadeOutTime": -1.0,
      "Segments": [
        0,
        0,
        1,
        0.944,
        0,
        1.889,
        0,
        2.833,
        0
      ]
    },
    {
      "Target": "Parameter",
      "Id": "Param127",
      "FadeInTime": -1.0,
      "FadeOutTime": -1.0,
      "Segments": [
        0,
        0,
        1,
        0.944,
        0,
        1.889,
        0,
        2.833,
        0
      ]
    },
    {
      "Target": "Parameter",
      "Id": "Paramring",
      "FadeInTime": -1.0,
      "FadeOutTime": -1.0,
      "Segments": [
        0,
        0,
        1,
        0.944,
        0,
        1.889,
        0,
        2.833,
        0
      ]
    },
    {
      "Target": "Parameter",
      "Id": "koushuishangxia",
      "FadeInTime": -1.0,
      "FadeOutTime": -1.0,
      "Segments": [
        0,
        0,
        1,
        0.944,
        0,
        1.889,
        0,
        2.833,
        0
      ]
    },
    {
      "Target": "Parameter",
      "Id": "koushuizuoyou",
      "FadeInTime": -1.0,
      "FadeOutTime": -1.0,
      "Segments": [
        0,
        0,
        1,
        0.944,
        0,
        1.889,
        0,
        2.833,
        0
      ]
    },
    {
      "Target": "Parameter",
      "Id": "koushuijiaodu",
      "FadeInTime": -1.0,
      "FadeOutTime": -1.0,
      "Segments": [
        0,
        0,
        1,
        0.944,
        0,
        1.889,
        0,
        2.833,
        0
      ]
    },
    {
      "Target": "Parameter",
      "Id": "koushuiyaobai",
      "FadeInTime": -1.0,
      "FadeOutTime": -1.0,
      "Segments": [
        0,
        0,
        1,
        0.944,
        0,
        1.889,
        0,
        2.833,
        0
      ]
    },
    {
      "Target": "Parameter",
      "Id": "koushuichangduan",
      "FadeInTime": -1.0,
      "FadeOutTime": -1.0,
      "Segments": [
        0,
        0,
        1,
        0.944,
        0,
        1.889,
        0,
        2.833,
        0
      ]
    },
    {
      "Target": "Parameter",
      "Id": "zhuhentmd",
      "FadeInTime": -1.0,
      "FadeOutTime": -1.0,
      "Segments": [
        0,
        0,
        1,
        0.944,
        0,
        1.889,
        0,
        2.833,
        0
      ]
    },
    {
      "Target": "Parameter",
      "Id": "zhuahenshensuo",
      "FadeInTime": -1.0,
      "FadeOutTime": -1.0,
      "Segments": [
        0,
        0,
        1,
        0.944,
        0,
        1.889,
        0,
        2.833,
        0
      ]
    },
    {
      "Target": "Parameter",
      "Id": "zhuahenjiaodu",
      "FadeInTime": -1.0,
      "FadeOutTime": -1.0,
      "Segments": [
        0,
        0,
        1,
        0.944,
        0,
        1.889,
        0,
        2.833,
        0
      ]
    },
    {
      "Target": "Parameter",
      "Id": "MouthX",
      "FadeInTime": -1.0,
      "FadeOutTime": -1.0,
      "Segments": [
        0,
        0,
        1,
        0.944,
        0,
        1.889,
        0,
        2.833,
        0
      ]
    },
    {
      "Target": "Parameter",
      "Id": "Param293",
      "FadeInTime": -1.0,
      "FadeOutTime": -1.0,
      "Segments": [
        0,
        0,
        1,
        0.944,
        0,
        1.889,
        0,
        2.833,
        0
      ]
    },
    {
      "Target": "Parameter",
      "Id": "MB_fenweiliangdu",
      "FadeInTime": -1.0,
      "FadeOutTime": -1.0,
      "Segments": [
        0,
        0.7,
        1,
        0.944,
        0.7,
        1.889,
        0.7,
        2.833,
        0.7
      ]
    },
    {
      "Target": "Parameter",
      "Id": "MB_fenweiandu",
      "FadeInTime": -1.0,
      "FadeOutTime": -1.0,
      "Segments": [
        0,
        0.6,
        1,
        0.944,
        0.6,
        1.889,
        0.6,
        2.833,
        0.6
      ]
    },
    {
      "Target": "Parameter",
      "Id": "MB_fenweiqiu1",
      "FadeInTime": -1.0,
      "FadeOutTime": -1.0,
      "Segments": [
        0,
        0.7,
        1,
        0.944,
        0.7,
        1.889,
        0.7,
        2.833,
        0.7
      ]
    },
    {
      "Target": "Parameter",
      "Id": "MB_fenweiqiu4",
      "FadeInTime": -1.0,
      "FadeOutTime": -1.0,
      "Segments": [
        0,
        0.7,
        1,
        0.944,
        0.7,
        1.889,
        0.7,
        2.833,
        0.7
      ]
    },
    {
      "Target": "Parameter",
      "Id": "MB_fenweiqiu2",
      "FadeInTime": -1.0,
      "FadeOutTime": -1.0,
      "Segments": [
        0,
        0.7,
        1,
        0.944,
        0.7,
        1.889,
        0.7,
        2.833,
        0.7
      ]
    },
    {
      "Target": "Parameter",
      "Id": "MB_fenweiqiu5",
      "FadeInTime": -1.0,
      "FadeOutTime": -1.0,
      "Segments": [
        0,
        0.7,
        1,
        0.944,
        0.7,
        1.889,
        0.7,
        2.833,
        0.7
      ]
    },
    {
      "Target": "Parameter",
      "Id": "MB_fenweiqiu3",
      "FadeInTime": -1.0,
      "FadeOutTime": -1.0,
      "Segments": [
        0,
        0.7,
        1,
        0.944,
        0.7,
        1.889,
        0.7,
        2.833,
        0.7
      ]
    },
    {
      "Target": "Parameter",
      "Id": "MB_fenweiqiu6",
      "FadeInTime": -1.0,
      "FadeOutTime": -1.0,
      "Segments": [
        0,
        0.7,
        1,
        0.944,
        0.7,
        1.889,
        0.7,
        2.833,
        0.7
      ]
    },
    {
      "Target": "Parameter",
      "Id": "MB_fenweiqiushangxia",
      "FadeInTime": -1.0,
      "FadeOutTime": -1.0,
      "Segments": [
        0,
        0,
        1,
        0.944,
        0,
        1.889,
        0,
        2.833,
        0
      ]
    },
    {
      "Target": "Parameter",
      "Id": "MB_fenweiqiudaxiao",
      "FadeInTime": -1.0,
      "FadeOutTime": -1.0,
      "Segments": [
        0,
        0,
        1,
        0.944,
        0,
        1.889,
        0,
        2.833,
        0
      ]
    },
    {
      "Target": "Parameter",
      "Id": "MB_fenweiTMD",
      "FadeInTime": -1.0,
      "FadeOutTime": -1.0,
      "Segments": [
        0,
        0,
        1,
        0.944,
        0,
        1.889,
        0,
        2.833,
        0
      ]
    },
    {
      "Target": "Parameter",
      "Id": "Param33",
      "FadeInTime": -1.0,
      "FadeOutTime": -1.0,
      "Segments": [
        0,
        0,
        1,
        0.944,
        0,
        1.889,
        0,
        2.833,
        0
      ]
    },
    {
      "Target": "Parameter",
      "Id": "Param26",
      "FadeInTime": -1.0,
      "FadeOutTime": -1.0,
      "Segments": [
        0,
        0,
        1,
        0.944,
        0,
        1.889,
        0,
        2.833,
        0
      ]
    },
    {
      "Target": "Parameter",
      "Id": "Param3",
      "FadeInTime": -1.0,
      "FadeOutTime": -1.0,
      "Segments": [
        0,
        0,
        1,
        0.944,
        0,
        1.889,
        0,
        2.833,
        0
      ]
    },
    {
      "Target": "Parameter",
      "Id": "Param24",
      "FadeInTime": -1.0,
      "FadeOutTime": -1.0,
      "Segments": [
        0,
        0,
        1,
        0.944,
        0,
        1.889,
        0,
        2.833,
        0
      ]
    },
    {
      "Target": "Parameter",
      "Id": "Param22",
      "FadeInTime": -1.0,
      "FadeOutTime": -1.0,
      "Segments": [
        0,
        0,
        1,
        0.944,
        0,
        1.889,
        0,
        2.833,
        0
      ]
    },
    {
      "Target": "Parameter",
      "Id": "Param23",
      "FadeInTime": -1.0,
      "FadeOutTime": -1.0,
      "Segments": [
        0,
        0,
        1,
        0.944,
        0,
        1.889,
        0,
        2.833,
        0
      ]
    },
    {
      "Target": "Parameter",
      "Id": "Param17",
      "FadeInTime": -1.0,
      "FadeOutTime": -1.0,
      "Segments": [
        0,
        0,
        1,
        0.944,
        0,
        1.889,
        0,
        2.833,
        0
      ]
    },
    {
      "Target": "Parameter",
      "Id": "Param19",
      "FadeInTime": -1.0,
      "FadeOutTime": -1.0,
      "Segments": [
        0,
        0,
        1,
        0.944,
        0,
        1.889,
        0,
        2.833,
        0
      ]
    },
    {
      "Target": "Parameter",
      "Id": "touch_drag40",
      "FadeInTime": -1.0,
      "FadeOutTime": -1.0,
      "Segments": [
        0,
        0,
        1,
        0.944,
        0,
        1.889,
        0,
        2.833,
        0
      ]
    },
    {
      "Target": "Parameter",
      "Id": "touch_drag41",
      "FadeInTime": -1.0,
      "FadeOutTime": -1.0,
      "Segments": [
        0,
        0,
        1,
        0.944,
        0,
        1.889,
        0,
        2.833,
        0
      ]
    },
    {
      "Target": "Parameter",
      "Id": "Param50",
      "FadeInTime": -1.0,
      "FadeOutTime": -1.0,
      "Segments": [
        0,
        0,
        1,
        0.944,
        0,
        1.889,
        0,
        2.833,
        0
      ]
    },
    {
      "Target": "Parameter",
      "Id": "Param21",
      "FadeInTime": -1.0,
      "FadeOutTime": -1.0,
      "Segments": [
        0,
        0,
        1,
        0.944,
        0,
        1.889,
        0,
        2.833,
        0
      ]
    },
    {
      "Target": "Parameter",
      "Id": "Param65",
      "FadeInTime": -1.0,
      "FadeOutTime": -1.0,
      "Segments": [
        0,
        0,
        1,
        0.944,
        0,
        1.889,
        0,
        2.833,
        0
      ]
    },
    {
      "Target": "Parameter",
      "Id": "Param52",
      "FadeInTime": -1.0,
      "FadeOutTime": -1.0,
      "Segments": [
        0,
        0,
        1,
        0.944,
        0,
        1.889,
        0,
        2.833,
        0
      ]
    },
    {
      "Target": "Parameter",
      "Id": "Param61",
      "FadeInTime": -1.0,
      "FadeOutTime": -1.0,
      "Segments": [
        0,
        0,
        1,
        0.944,
        0,
        1.889,
        0,
        2.833,
        0
      ]
    },
    {
      "Target": "Parameter",
      "Id": "Param53",
      "FadeInTime": -1.0,
      "FadeOutTime": -1.0,
      "Segments": [
        0,
        0,
        1,
        0.944,
        0,
        1.889,
        0,
        2.833,
        0
      ]
    },
    {
      "Target": "Parameter",
      "Id": "Param42",
      "FadeInTime": -1.0,
      "FadeOutTime": -1.0,
      "Segments": [
        0,
        0,
        1,
        0.944,
        0,
        1.889,
        0,
        2.833,
        0
      ]
    },
    {
      "Target": "Parameter",
      "Id": "Param67",
      "FadeInTime": -1.0,
      "FadeOutTime": -1.0,
      "Segments": [
        0,
        0,
        1,
        0.944,
        0,
        1.889,
        0,
        2.833,
        0
      ]
    },
    {
      "Target": "Parameter",
      "Id": "Param68",
      "FadeInTime": -1.0,
      "FadeOutTime": -1.0,
      "Segments": [
        0,
        0,
        1,
        0.944,
        0,
        1.889,
        0,
        2.833,
        0
      ]
    },
    {
      "Target": "Parameter",
      "Id": "Param69",
      "FadeInTime": -1.0,
      "FadeOutTime": -1.0,
      "Segments": [
        0,
        0,
        1,
        0.944,
        0,
        1.889,
        0,
        2.833,
        0
      ]
    },
    {
      "Target": "Parameter",
      "Id": "ParamNeckZ3",
      "FadeInTime": -1.0,
      "FadeOutTime": -1.0,
      "Segments": [
        0,
        30,
        1,
        0.944,
        30,
        1.889,
        30,
        2.833,
        30
      ]
    },
    {
      "Target": "Parameter",
      "Id": "Param63",
      "FadeInTime": -1.0,
      "FadeOutTime": -1.0,
      "Segments": [
        0,
        -0.056,
        1,
        0.944,
        -0.056,
        1.889,
        -0.056,
        2.833,
        -0.056
      ]
    },
    {
      "Target": "Parameter",
      "Id": "ParamLowerBodyZ",
      "FadeInTime": -1.0,
      "FadeOutTime": -1.0,
      "Segments": [
        0,
        5.287,
        1,
        0.944,
        5.287,
        1.889,
        5.287,
        2.833,
        5.287
      ]
    },
    {
      "Target": "Parameter",
      "Id": "ParamLowerBodyY",
      "FadeInTime": -1.0,
      "FadeOutTime": -1.0,
      "Segments": [
        0,
        5.906,
        1,
        0.944,
        5.906,
        1.889,
        5.906,
        2.833,
        5.906
      ]
    },
    {
      "Target": "Parameter",
      "Id": "Param34",
      "FadeInTime": -1.0,
      "FadeOutTime": -1.0,
      "Segments": [
        0,
        0,
        1,
        0.944,
        0,
        1.889,
        0,
        2.833,
        0
      ]
    },
    {
      "Target": "Parameter",
      "Id": "Param35",
      "FadeInTime": -1.0,
      "FadeOutTime": -1.0,
      "Segments": [
        0,
        0,
        1,
        0.944,
        0,
        1.889,
        0,
        2.833,
        0
      ]
    },
    {
      "Target": "Parameter",
      "Id": "Param14",
      "FadeInTime": -1.0,
      "FadeOutTime": -1.0,
      "Segments": [
        0,
        0,
        1,
        0.944,
        0,
        1.889,
        0,
        2.833,
        0
      ]
    },
    {
      "Target": "Parameter",
      "Id": "Param18",
      "FadeInTime": -1.0,
      "FadeOutTime": -1.0,
      "Segments": [
        0,
        0,
        1,
        0.944,
        0,
        1.889,
        0,
        2.833,
        0
      ]
    },
    {
      "Target": "Parameter",
      "Id": "Param143",
      "FadeInTime": -1.0,
      "FadeOutTime": -1.0,
      "Segments": [
        0,
        0,
        1,
        0.944,
        0,
        1.889,
        0,
        2.833,
        0
      ]
    },
    {
      "Target": "Parameter",
      "Id": "Param25",
      "FadeInTime": -1.0,
      "FadeOutTime": -1.0,
      "Segments": [
        0,
        0,
        1,
        0.944,
        0,
        1.889,
        0,
        2.833,
        0
      ]
    },
    {
      "Target": "Parameter",
      "Id": "ParamForearmRChange2",
      "FadeInTime": -1.0,
      "FadeOutTime": -1.0,
      "Segments": [
        0,
        0,
        1,
        0.944,
        0,
        1.889,
        0,
        2.833,
        0
      ]
    },
    {
      "Target": "Parameter",
      "Id": "ParamArmRStretch",
      "FadeInTime": -1.0,
      "FadeOutTime": -1.0,
      "Segments": [
        0,
        0,
        1,
        0.944,
        0,
        1.889,
        0,
        2.833,
        0
      ]
    },
    {
      "Target": "Parameter",
      "Id": "ParamHandR1Change",
      "FadeInTime": -1.0,
      "FadeOutTime": -1.0,
      "Segments": [
        0,
        0,
        1,
        0.944,
        0,
        1.889,
        0,
        2.833,
        0
      ]
    },
    {
      "Target": "Parameter",
      "Id": "ParamHandRChange",
      "FadeInTime": -1.0,
      "FadeOutTime": -1.0,
      "Segments": [
        0,
        0,
        1,
        0.944,
        0,
        1.889,
        0,
        2.833,
        0
      ]
    },
    {
      "Target": "Parameter",
      "Id": "ParamHandR_SZ",
      "FadeInTime": -1.0,
      "FadeOutTime": -1.0,
      "Segments": [
        0,
        0,
        1,
        0.944,
        0,
        1.889,
        0,
        2.833,
        0
      ]
    },
    {
      "Target": "Parameter",
      "Id": "ParamHandR_HZ",
      "FadeInTime": -1.0,
      "FadeOutTime": -1.0,
      "Segments": [
        0,
        0,
        1,
        0.944,
        0,
        1.889,
        0,
        2.833,
        0
      ]
    },
    {
      "Target": "Parameter",
      "Id": "Param101",
      "FadeInTime": -1.0,
      "FadeOutTime": -1.0,
      "Segments": [
        0,
        0,
        1,
        0.944,
        0,
        1.889,
        0,
        2.833,
        0
      ]
    },
    {
      "Target": "Parameter",
      "Id": "Param41",
      "FadeInTime": -1.0,
      "FadeOutTime": -1.0,
      "Segments": [
        0,
        0,
        1,
        0.944,
        0,
        1.889,
        0,
        2.833,
        0
      ]
    },
    {
      "Target": "Parameter",
      "Id": "Param59",
      "FadeInTime": -1.0,
      "FadeOutTime": -1.0,
      "Segments": [
        0,
        -2.333,
        1,
        0.944,
        -2.333,
        1.889,
        -2.333,
        2.833,
        -2.333
      ]
    },
    {
      "Target": "Parameter",
      "Id": "Param60",
      "FadeInTime": -1.0,
      "FadeOutTime": -1.0,
      "Segments": [
        0,
        6.822,
        1,
        0.944,
        6.822,
        1.889,
        6.822,
        2.833,
        6.822
      ]
    },
    {
      "Target": "Parameter",
      "Id": "Param36",
      "FadeInTime": -1.0,
      "FadeOutTime": -1.0,
      "Segments": [
        0,
        0,
        1,
        0.944,
        0,
        1.889,
        0,
        2.833,
        0
      ]
    },
    {
      "Target": "Parameter",
      "Id": "Param47",
      "FadeInTime": -1.0,
      "FadeOutTime": -1.0,
      "Segments": [
        0,
        15,
        1,
        0.944,
        15,
        1.889,
        15,
        2.833,
        15
      ]
    },
    {
      "Target": "Parameter",
      "Id": "ParamForearmRChange3",
      "FadeInTime": -1.0,
      "FadeOutTime": -1.0,
      "Segments": [
        0,
        0,
        1,
        0.944,
        0,
        1.889,
        0,
        2.833,
        0
      ]
    },
    {
      "Target": "Parameter",
      "Id": "ParamForearmRChange4",
      "FadeInTime": -1.0,
      "FadeOutTime": -1.0,
      "Segments": [
        0,
        -15,
        1,
        0.944,
        -15,
        1.889,
        -15,
        2.833,
        -15
      ]
    },
    {
      "Target": "Parameter",
      "Id": "Param6",
      "FadeInTime": -1.0,
      "FadeOutTime": -1.0,
      "Segments": [
        0,
        13.62,
        1,
        0.944,
        13.62,
        1.889,
        13.62,
        2.833,
        13.62
      ]
    },
    {
      "Target": "Parameter",
      "Id": "ParamHandRREDisplay2",
      "FadeInTime": -1.0,
      "FadeOutTime": -1.0,
      "Segments": [
        0,
        20,
        1,
        0.944,
        20,
        1.889,
        20,
        2.833,
        20
      ]
    },
    {
      "Target": "Parameter",
      "Id": "ParamHandR1Change2",
      "FadeInTime": -1.0,
      "FadeOutTime": -1.0,
      "Segments": [
        0,
        -8,
        1,
        0.944,
        -8,
        1.889,
        -8,
        2.833,
        -8
      ]
    },
    {
      "Target": "Parameter",
      "Id": "ParamHandRAnimation2",
      "FadeInTime": -1.0,
      "FadeOutTime": -1.0,
      "Segments": [
        0,
        30,
        1,
        0.944,
        30,
        1.889,
        30,
        2.833,
        30
      ]
    },
    {
      "Target": "Parameter",
      "Id": "ParamHandRChange2",
      "FadeInTime": -1.0,
      "FadeOutTime": -1.0,
      "Segments": [
        0,
        0,
        1,
        0.944,
        0,
        1.889,
        0,
        2.833,
        0
      ]
    },
    {
      "Target": "Parameter",
      "Id": "ParamHandR_SZ2",
      "FadeInTime": -1.0,
      "FadeOutTime": -1.0,
      "Segments": [
        0,
        -4,
        1,
        0.944,
        -4,
        1.889,
        -4,
        2.833,
        -4
      ]
    },
    {
      "Target": "Parameter",
      "Id": "ParamHandR_HZ2",
      "FadeInTime": -1.0,
      "FadeOutTime": -1.0,
      "Segments": [
        0,
        -1,
        1,
        0.944,
        -1,
        1.889,
        -1,
        2.833,
        -1
      ]
    },
    {
      "Target": "Parameter",
      "Id": "Param124",
      "FadeInTime": -1.0,
      "FadeOutTime": -1.0,
      "Segments": [
        0,
        0,
        1,
        0.944,
        0,
        1.889,
        0,
        2.833,
        0
      ]
    },
    {
      "Target": "Parameter",
      "Id": "Param66",
      "FadeInTime": -1.0,
      "FadeOutTime": -1.0,
      "Segments": [
        0,
        0,
        1,
        0.944,
        0,
        1.889,
        0,
        2.833,
        0
      ]
    },
    {
      "Target": "Parameter",
      "Id": "Param144",
      "FadeInTime": -1.0,
      "FadeOutTime": -1.0,
      "Segments": [
        0,
        0,
        1,
        0.944,
        0,
        1.889,
        0,
        2.833,
        0
      ]
    },
    {
      "Target": "Parameter",
      "Id": "Param8",
      "FadeInTime": -1.0,
      "FadeOutTime": -1.0,
      "Segments": [
        0,
        0,
        1,
        0.944,
        0,
        1.889,
        0,
        2.833,
        0
      ]
    },
    {
      "Target": "Parameter",
      "Id": "Param57",
      "FadeInTime": -1.0,
      "FadeOutTime": -1.0,
      "Segments": [
        0,
        0,
        1,
        0.944,
        0,
        1.889,
        0,
        2.833,
        0
      ]
    },
    {
      "Target": "Parameter",
      "Id": "Param132",
      "FadeInTime": -1.0,
      "FadeOutTime": -1.0,
      "Segments": [
        0,
        0,
        1,
        0.944,
        0,
        1.889,
        0,
        2.833,
        0
      ]
    },
    {
      "Target": "Parameter",
      "Id": "Param38",
      "FadeInTime": -1.0,
      "FadeOutTime": -1.0,
      "Segments": [
        0,
        0,
        1,
        0.944,
        0,
        1.889,
        0,
        2.833,
        0
      ]
    },
    {
      "Target": "Parameter",
      "Id": "Param40",
      "FadeInTime": -1.0,
      "FadeOutTime": -1.0,
      "Segments": [
        0,
        0,
        1,
        0.944,
        0,
        1.889,
        0,
        2.833,
        0
      ]
    },
    {
      "Target": "Parameter",
      "Id": "Param133",
      "FadeInTime": -1.0,
      "FadeOutTime": -1.0,
      "Segments": [
        0,
        30,
        1,
        0.944,
        30,
        1.889,
        30,
        2.833,
        30
      ]
    },
    {
      "Target": "Parameter",
      "Id": "Param135",
      "FadeInTime": -1.0,
      "FadeOutTime": -1.0,
      "Segments": [
        0,
        0,
        1,
        0.944,
        0,
        1.889,
        0,
        2.833,
        0
      ]
    },
    {
      "Target": "Parameter",
      "Id": "Param9",
      "FadeInTime": -1.0,
      "FadeOutTime": -1.0,
      "Segments": [
        0,
        8.122,
        1,
        0.944,
        8.122,
        1.889,
        8.122,
        2.833,
        8.122
      ]
    },
    {
      "Target": "Parameter",
      "Id": "Param10",
      "FadeInTime": -1.0,
      "FadeOutTime": -1.0,
      "Segments": [
        0,
        2.11,
        1,
        0.944,
        2.11,
        1.889,
        2.11,
        2.833,
        2.11
      ]
    },
    {
      "Target": "Parameter",
      "Id": "Param4",
      "FadeInTime": -1.0,
      "FadeOutTime": -1.0,
      "Segments": [
        0,
        -4.098,
        1,
        0.944,
        -4.098,
        1.889,
        -4.098,
        2.833,
        -4.098
      ]
    },
    {
      "Target": "Parameter",
      "Id": "Param7",
      "FadeInTime": -1.0,
      "FadeOutTime": -1.0,
      "Segments": [
        0,
        6.732,
        1,
        0.944,
        6.732,
        1.889,
        6.732,
        2.833,
        6.732
      ]
    },
    {
      "Target": "Parameter",
      "Id": "Param48",
      "FadeInTime": -1.0,
      "FadeOutTime": -1.0,
      "Segments": [
        0,
        0,
        1,
        0.944,
        0,
        1.889,
        0,
        2.833,
        0
      ]
    },
    {
      "Target": "Parameter",
      "Id": "Param128",
      "FadeInTime": -1.0,
      "FadeOutTime": -1.0,
      "Segments": [
        0,
        0,
        1,
        0.944,
        0,
        1.889,
        0,
        2.833,
        0
      ]
    },
    {
      "Target": "Parameter",
      "Id": "Param39",
      "FadeInTime": -1.0,
      "FadeOutTime": -1.0,
      "Segments": [
        0,
        -0.635,
        1,
        0.944,
        -0.635,
        1.889,
        -0.635,
        2.833,
        -0.635
      ]
    },
    {
      "Target": "Parameter",
      "Id": "Param37",
      "FadeInTime": -1.0,
      "FadeOutTime": -1.0,
      "Segments": [
        0,
        0,
        1,
        0.944,
        0,
        1.889,
        0,
        2.833,
        0
      ]
    },
    {
      "Target": "Parameter",
      "Id": "Param16",
      "FadeInTime": -1.0,
      "FadeOutTime": -1.0,
      "Segments": [
        0,
        0,
        1,
        0.944,
        0,
        1.889,
        0,
        2.833,
        0
      ]
    },
    {
      "Target": "Parameter",
      "Id": "Param129",
      "FadeInTime": -1.0,
      "FadeOutTime": -1.0,
      "Segments": [
        0,
        30,
        1,
        0.944,
        30,
        1.889,
        30,
        2.833,
        30
      ]
    },
    {
      "Target": "Parameter",
      "Id": "Param131",
      "FadeInTime": -1.0,
      "FadeOutTime": -1.0,
      "Segments": [
        0,
        0,
        1,
        0.944,
        0,
        1.889,
        0,
        2.833,
        0
      ]
    },
    {
      "Target": "Parameter",
      "Id": "Param11",
      "FadeInTime": -1.0,
      "FadeOutTime": -1.0,
      "Segments": [
        0,
        -8.437,
        1,
        0.944,
        -8.437,
        1.889,
        -8.437,
        2.833,
        -8.437
      ]
    },
    {
      "Target": "Parameter",
      "Id": "Param13",
      "FadeInTime": -1.0,
      "FadeOutTime": -1.0,
      "Segments": [
        0,
        2.515,
        1,
        0.944,
        2.515,
        1.889,
        2.515,
        2.833,
        2.515
      ]
    },
    {
      "Target": "Parameter",
      "Id": "Param",
      "FadeInTime": -1.0,
      "FadeOutTime": -1.0,
      "Segments": [
        0,
        3.752,
        1,
        0.944,
        3.752,
        1.889,
        3.752,
        2.833,
        3.752
      ]
    },
    {
      "Target": "Parameter",
      "Id": "Param2",
      "FadeInTime": -1.0,
      "FadeOutTime": -1.0,
      "Segments": [
        0,
        6.834,
        1,
        0.944,
        6.834,
        1.889,
        6.834,
        2.833,
        6.834
      ]
    },
    {
      "Target": "Parameter",
      "Id": "ParamCheek",
      "FadeInTime": -1.0,
      "FadeOutTime": -1.0,
      "Segments": [
        0,
        0,
        1,
        0.944,
        0,
        1.889,
        0,
        2.833,
        0
      ]
    },
    {
      "Target": "Parameter",
      "Id": "Param106",
      "FadeInTime": -1.0,
      "FadeOutTime": -1.0,
      "Segments": [
        0,
        0,
        1,
        0.944,
        0,
        1.889,
        0,
        2.833,
        0
      ]
    },
    {
      "Target": "Parameter",
      "Id": "Param125",
      "FadeInTime": -1.0,
      "FadeOutTime": -1.0,
      "Segments": [
        0,
        0,
        1,
        0.944,
        0,
        1.889,
        0,
        2.833,
        0
      ]
    },
    {
      "Target": "Parameter",
      "Id": "Param171",
      "FadeInTime": -1.0,
      "FadeOutTime": -1.0,
      "Segments": [
        0,
        0,
        1,
        0.944,
        0,
        1.889,
        0,
        2.833,
        0
      ]
    },
    {
      "Target": "Parameter",
      "Id": "Param166",
      "FadeInTime": -1.0,
      "FadeOutTime": -1.0,
      "Segments": [
        0,
        0,
        1,
        0.944,
        0,
        1.889,
        0,
        2.833,
        0
      ]
    },
    {
      "Target": "Parameter",
      "Id": "Param123",
      "FadeInTime": -1.0,
      "FadeOutTime": -1.0,
      "Segments": [
        0,
        0,
        1,
        0.944,
        0,
        1.889,
        0,
        2.833,
        0
      ]
    },
    {
      "Target": "Parameter",
      "Id": "ParamEyeLSmile",
      "FadeInTime": -1.0,
      "FadeOutTime": -1.0,
      "Segments": [
        0,
        0,
        1,
        0.944,
        0,
        1.889,
        0,
        2.833,
        0
      ]
    },
    {
      "Target": "Parameter",
      "Id": "ParamEyeRSmile",
      "FadeInTime": -1.0,
      "FadeOutTime": -1.0,
      "Segments": [
        0,
        0,
        1,
        0.944,
        0,
        1.889,
        0,
        2.833,
        0
      ]
    },
    {
      "Target": "Parameter",
      "Id": "ParamEyeBallX",
      "FadeInTime": -1.0,
      "FadeOutTime": -1.0,
      "Segments": [
        0,
        0,
        1,
        0.944,
        0,
        1.889,
        0,
        2.833,
        0
      ]
    },
    {
      "Target": "Parameter",
      "Id": "ParamEyeBallY",
      "FadeInTime": -1.0,
      "FadeOutTime": -1.0,
      "Segments": [
        0,
        0,
        1,
        0.944,
        0,
        1.889,
        0,
        2.833,
        0
      ]
    },
    {
      "Target": "Parameter",
      "Id": "ParamEyeBallX1",
      "FadeInTime": -1.0,
      "FadeOutTime": -1.0,
      "Segments": [
        0,
        0,
        1,
        0.944,
        0,
        1.889,
        0,
        2.833,
        0
      ]
    },
    {
      "Target": "Parameter",
      "Id": "ParamEyeBallY1",
      "FadeInTime": -1.0,
      "FadeOutTime": -1.0,
      "Segments": [
        0,
        0,
        1,
        0.944,
        0,
        1.889,
        0,
        2.833,
        0
      ]
    },
    {
      "Target": "Parameter",
      "Id": "ParamBrowLForm2",
      "FadeInTime": -1.0,
      "FadeOutTime": -1.0,
      "Segments": [
        0,
        0,
        1,
        0.944,
        0,
        1.889,
        0,
        2.833,
        0
      ]
    },
    {
      "Target": "Parameter",
      "Id": "ParamBrowLForm",
      "FadeInTime": -1.0,
      "FadeOutTime": -1.0,
      "Segments": [
        0,
        -0.163,
        1,
        0.944,
        -0.163,
        1.889,
        -0.163,
        2.833,
        -0.163
      ]
    },
    {
      "Target": "Parameter",
      "Id": "ParamBrowLAngle",
      "FadeInTime": -1.0,
      "FadeOutTime": -1.0,
      "Segments": [
        0,
        0.307,
        1,
        0.944,
        0.307,
        1.889,
        0.307,
        2.833,
        0.307
      ]
    },
    {
      "Target": "Parameter",
      "Id": "Param62",
      "FadeInTime": -1.0,
      "FadeOutTime": -1.0,
      "Segments": [
        0,
        0,
        1,
        0.944,
        0,
        1.889,
        0,
        2.833,
        0
      ]
    },
    {
      "Target": "Parameter",
      "Id": "Param15",
      "FadeInTime": -1.0,
      "FadeOutTime": -1.0,
      "Segments": [
        0,
        -1,
        1,
        0.944,
        -1,
        1.889,
        -1,
        2.833,
        -1
      ]
    },
    {
      "Target": "Parameter",
      "Id": "Hair_physics",
      "FadeInTime": -1.0,
      "FadeOutTime": -1.0,
      "Segments": [
        0,
        0,
        1,
        0.944,
        0,
        1.889,
        0,
        2.833,
        0
      ]
    },
    {
      "Target": "Parameter",
      "Id": "Hair_physics2",
      "FadeInTime": -1.0,
      "FadeOutTime": -1.0,
      "Segments": [
        0,
        0,
        1,
        0.944,
        0,
        1.889,
        0,
        2.833,
        0
      ]
    },
    {
      "Target": "Parameter",
      "Id": "Param30",
      "FadeInTime": -1.0,
      "FadeOutTime": -1.0,
      "Segments": [
        0,
        1,
        1,
        0.944,
        1,
        1.889,
        1,
        2.833,
        1
      ]
    },
    {
      "Target": "Parameter",
      "Id": "Param31",
      "FadeInTime": -1.0,
      "FadeOutTime": -1.0,
      "Segments": [
        0,
        1,
        1,
        0.944,
        1,
        1.889,
        1,
        2.833,
        1
      ]
    },
    {
      "Target": "Parameter",
      "Id": "Param29",
      "FadeInTime": -1.0,
      "FadeOutTime": -1.0,
      "Segments": [
        0,
        1,
        1,
        0.944,
        1,
        1.889,
        1,
        2.833,
        1
      ]
    },
    {
      "Target": "Parameter",
      "Id": "ParamEyelash1",
      "FadeInTime": -1.0,
      "FadeOutTime": -1.0,
      "Segments": [
        0,
        0,
        1,
        0.944,
        0,
        1.889,
        0,
        2.833,
        0
      ]
    },
    {
      "Target": "Parameter",
      "Id": "ParamEyeOpen_physics",
      "FadeInTime": -1.0,
      "FadeOutTime": -1.0,
      "Segments": [
        0,
        0,
        1,
        0.944,
        0,
        1.889,
        0,
        2.833,
        0
      ]
    },
    {
      "Target": "Parameter",
      "Id": "ParamEyeBallY_physics",
      "FadeInTime": -1.0,
      "FadeOutTime": -1.0,
      "Segments": [
        0,
        0,
        1,
        0.944,
        0,
        1.889,
        0,
        2.833,
        0
      ]
    },
    {
      "Target": "Parameter",
      "Id": "ParamEyeFormY2",
      "FadeInTime": -1.0,
      "FadeOutTime": -1.0,
      "Segments": [
        0,
        0,
        1,
        0.944,
        0,
        1.889,
        0,
        2.833,
        0
      ]
    },
    {
      "Target": "Parameter",
      "Id": "ParamEyeBallSize_physics",
      "FadeInTime": -1.0,
      "FadeOutTime": -1.0,
      "Segments": [
        0,
        0,
        1,
        0.944,
        0,
        1.889,
        0,
        2.833,
        0
      ]
    },
    {
      "Target": "Parameter",
      "Id": "ParamEyeBall_lightB",
      "FadeInTime": -1.0,
      "FadeOutTime": -1.0,
      "Segments": [
        0,
        0,
        1,
        0.944,
        0,
        1.889,
        0,
        2.833,
        0
      ]
    },
    {
      "Target": "Parameter",
      "Id": "Param180",
      "FadeInTime": -1.0,
      "FadeOutTime": -1.0,
      "Segments": [
        0,
        0,
        1,
        0.944,
        0,
        1.889,
        0,
        2.833,
        0
      ]
    },
    {
      "Target": "Parameter",
      "Id": "Param181",
      "FadeInTime": -1.0,
      "FadeOutTime": -1.0,
      "Segments": [
        0,
        0,
        1,
        0.944,
        0,
        1.889,
        0,
        2.833,
        0
      ]
    },
    {
      "Target": "Parameter",
      "Id": "Param182",
      "FadeInTime": -1.0,
      "FadeOutTime": -1.0,
      "Segments": [
        0,
        0,
        1,
        0.944,
        0,
        1.889,
        0,
        2.833,
        0
      ]
    },
    {
      "Target": "Parameter",
      "Id": "Param183",
      "FadeInTime": -1.0,
      "FadeOutTime": -1.0,
      "Segments": [
        0,
        0,
        1,
        0.944,
        0,
        1.889,
        0,
        2.833,
        0
      ]
    },
    {
      "Target": "Parameter",
      "Id": "ZX13",
      "FadeInTime": -1.0,
      "FadeOutTime": -1.0,
      "Segments": [
        0,
        0,
        1,
        0.944,
        0,
        1.889,
        0,
        2.833,
        0
      ]
    },
    {
      "Target": "Parameter",
      "Id": "ZX14",
      "FadeInTime": -1.0,
      "FadeOutTime": -1.0,
      "Segments": [
        0,
        0,
        1,
        0.944,
        0,
        1.889,
        0,
        2.833,
        0
      ]
    },
    {
      "Target": "Parameter",
      "Id": "ZX15",
      "FadeInTime": -1.0,
      "FadeOutTime": -1.0,
      "Segments": [
        0,
        0,
        1,
        0.944,
        0,
        1.889,
        0,
        2.833,
        0
      ]
    },
    {
      "Target": "Parameter",
      "Id": "ZX16",
      "FadeInTime": -1.0,
      "FadeOutTime": -1.0,
      "Segments": [
        0,
        0,
        1,
        0.944,
        0,
        1.889,
        0,
        2.833,
        0
      ]
    },
    {
      "Target": "Parameter",
      "Id": "ZX9",
      "FadeInTime": -1.0,
      "FadeOutTime": -1.0,
      "Segments": [
        0,
        0,
        1,
        0.944,
        0,
        1.889,
        0,
        2.833,
        0
      ]
    },
    {
      "Target": "Parameter",
      "Id": "ZX10",
      "FadeInTime": -1.0,
      "FadeOutTime": -1.0,
      "Segments": [
        0,
        0,
        1,
        0.944,
        0,
        1.889,
        0,
        2.833,
        0
      ]
    },
    {
      "Target": "Parameter",
      "Id": "ZX11",
      "FadeInTime": -1.0,
      "FadeOutTime": -1.0,
      "Segments": [
        0,
        0,
        1,
        0.944,
        0,
        1.889,
        0,
        2.833,
        0
      ]
    },
    {
      "Target": "Parameter",
      "Id": "ZX12",
      "FadeInTime": -1.0,
      "FadeOutTime": -1.0,
      "Segments": [
        0,
        0,
        1,
        0.944,
        0,
        1.889,
        0,
        2.833,
        0
      ]
    },
    {
      "Target": "Parameter",
      "Id": "YX1",
      "FadeInTime": -1.0,
      "FadeOutTime": -1.0,
      "Segments": [
        0,
        0,
        1,
        0.944,
        0,
        1.889,
        0,
        2.833,
        0
      ]
    },
    {
      "Target": "Parameter",
      "Id": "YX2",
      "FadeInTime": -1.0,
      "FadeOutTime": -1.0,
      "Segments": [
        0,
        0,
        1,
        0.944,
        0,
        1.889,
        0,
        2.833,
        0
      ]
    },
    {
      "Target": "Parameter",
      "Id": "YX3",
      "FadeInTime": -1.0,
      "FadeOutTime": -1.0,
      "Segments": [
        0,
        0,
        1,
        0.944,
        0,
        1.889,
        0,
        2.833,
        0
      ]
    },
    {
      "Target": "Parameter",
      "Id": "YX4",
      "FadeInTime": -1.0,
      "FadeOutTime": -1.0,
      "Segments": [
        0,
        0,
        1,
        0.944,
        0,
        1.889,
        0,
        2.833,
        0
      ]
    },
    {
      "Target": "Parameter",
      "Id": "YX5",
      "FadeInTime": -1.0,
      "FadeOutTime": -1.0,
      "Segments": [
        0,
        0,
        1,
        0.944,
        0,
        1.889,
        0,
        2.833,
        0
      ]
    },
    {
      "Target": "Parameter",
      "Id": "YX6",
      "FadeInTime": -1.0,
      "FadeOutTime": -1.0,
      "Segments": [
        0,
        0,
        1,
        0.944,
        0,
        1.889,
        0,
        2.833,
        0
      ]
    },
    {
      "Target": "Parameter",
      "Id": "YX7",
      "FadeInTime": -1.0,
      "FadeOutTime": -1.0,
      "Segments": [
        0,
        0,
        1,
        0.944,
        0,
        1.889,
        0,
        2.833,
        0
      ]
    },
    {
      "Target": "Parameter",
      "Id": "ZX1",
      "FadeInTime": -1.0,
      "FadeOutTime": -1.0,
      "Segments": [
        0,
        0,
        1,
        0.944,
        0,
        1.889,
        0,
        2.833,
        0
      ]
    },
    {
      "Target": "Parameter",
      "Id": "ZX2",
      "FadeInTime": -1.0,
      "FadeOutTime": -1.0,
      "Segments": [
        0,
        0,
        1,
        0.944,
        0,
        1.889,
        0,
        2.833,
        0
      ]
    },
    {
      "Target": "Parameter",
      "Id": "ZX3",
      "FadeInTime": -1.0,
      "FadeOutTime": -1.0,
      "Segments": [
        0,
        0,
        1,
        0.944,
        0,
        1.889,
        0,
        2.833,
        0
      ]
    },
    {
      "Target": "Parameter",
      "Id": "ZX4",
      "FadeInTime": -1.0,
      "FadeOutTime": -1.0,
      "Segments": [
        0,
        0,
        1,
        0.944,
        0,
        1.889,
        0,
        2.833,
        0
      ]
    },
    {
      "Target": "Parameter",
      "Id": "ZX5",
      "FadeInTime": -1.0,
      "FadeOutTime": -1.0,
      "Segments": [
        0,
        0,
        1,
        0.944,
        0,
        1.889,
        0,
        2.833,
        0
      ]
    },
    {
      "Target": "Parameter",
      "Id": "ZX6",
      "FadeInTime": -1.0,
      "FadeOutTime": -1.0,
      "Segments": [
        0,
        0,
        1,
        0.944,
        0,
        1.889,
        0,
        2.833,
        0
      ]
    },
    {
      "Target": "Parameter",
      "Id": "ZX7",
      "FadeInTime": -1.0,
      "FadeOutTime": -1.0,
      "Segments": [
        0,
        0,
        1,
        0.944,
        0,
        1.889,
        0,
        2.833,
        0
      ]
    },
    {
      "Target": "Parameter",
      "Id": "ZX8",
      "FadeInTime": -1.0,
      "FadeOutTime": -1.0,
      "Segments": [
        0,
        0,
        1,
        0.944,
        0,
        1.889,
        0,
        2.833,
        0
      ]
    },
    {
      "Target": "Parameter",
      "Id": "Param205",
      "FadeInTime": -1.0,
      "FadeOutTime": -1.0,
      "Segments": [
        0,
        1,
        1,
        0.944,
        1,
        1.889,
        1,
        2.833,
        1
      ]
    },
    {
      "Target": "Parameter",
      "Id": "Param210",
      "FadeInTime": -1.0,
      "FadeOutTime": -1.0,
      "Segments": [
        0,
        1,
        1,
        0.944,
        1,
        1.889,
        1,
        2.833,
        1
      ]
    },
    {
      "Target": "Parameter",
      "Id": "Param56",
      "FadeInTime": -1.0,
      "FadeOutTime": -1.0,
      "Segments": [
        0,
        0,
        1,
        0.944,
        0,
        1.889,
        0,
        2.833,
        0
      ]
    },
    {
      "Target": "Parameter",
      "Id": "Param55",
      "FadeInTime": -1.0,
      "FadeOutTime": -1.0,
      "Segments": [
        0,
        0,
        1,
        0.944,
        0,
        1.889,
        0,
        2.833,
        0
      ]
    },
    {
      "Target": "Parameter",
      "Id": "MB_Awutifanzhuan",
      "FadeInTime": -1.0,
      "FadeOutTime": -1.0,
      "Segments": [
        0,
        -1,
        1,
        0.944,
        -1,
        1.889,
        -1,
        2.833,
        -1
      ]
    },
    {
      "Target": "Parameter",
      "Id": "Param27",
      "FadeInTime": -1.0,
      "FadeOutTime": -1.0,
      "Segments": [
        0,
        0,
        1,
        0.944,
        0,
        1.889,
        0,
        2.833,
        0
      ]
    },
    {
      "Target": "Parameter",
      "Id": "ParamBreath",
      "FadeInTime": -1.0,
      "FadeOutTime": -1.0,
      "Segments": [
        0,
        0,
        1,
        0.944,
        0,
        1.889,
        0,
        2.833,
        0
      ]
    },
    {
      "Target": "Parameter",
      "Id": "empty1",
      "FadeInTime": -1.0,
      "FadeOutTime": -1.0,
      "Segments": [
        0,
        0,
        1,
        0.944,
        0,
        1.889,
        0,
        2.833,
        0
      ]
    },
    {
      "Target": "Parameter",
      "Id": "empty2",
      "FadeInTime": -1.0,
      "FadeOutTime": -1.0,
      "Segments": [
        0,
        0,
        1,
        0.944,
        0,
        1.889,
        0,
        2.833,
        0
      ]
    },
    {
      "Target": "Parameter",
      "Id": "empty3",
      "FadeInTime": -1.0,
      "FadeOutTime": -1.0,
      "Segments": [
        0,
        0,
        1,
        0.944,
        0,
        1.889,
        0,
        2.833,
        0
      ]
    },
    {
      "Target": "Parameter",
      "Id": "empty4",
      "FadeInTime": -1.0,
      "FadeOutTime": -1.0,
      "Segments": [
        0,
        0,
        1,
        0.944,
        0,
        1.889,
        0,
        2.833,
        0
      ]
    },
    {
      "Target": "Parameter",
      "Id": "empty5",
      "FadeInTime": -1.0,
      "FadeOutTime": -1.0,
      "Segments": [
        0,
        0,
        1,
        0.944,
        0,
        1.889,
        0,
        2.833,
        0
      ]
    },
    {
      "Target": "Parameter",
      "Id": "empty6",
      "FadeInTime": -1.0,
      "FadeOutTime": -1.0,
      "Segments": [
        0,
        0,
        1,
        0.944,
        0,
        1.889,
        0,
        2.833,
        0
      ]
    },
    {
      "Target": "Parameter",
      "Id": "empty7",
      "FadeInTime": -1.0,
      "FadeOutTime": -1.0,
      "Segments": [
        0,
        0,
        1,
        0.944,
        0,
        1.889,
        0,
        2.833,
        0
      ]
    },
    {
      "Target": "Parameter",
      "Id": "empty8",
      "FadeInTime": -1.0,
      "FadeOutTime": -1.0,
      "Segments": [
        0,
        0,
        1,
        0.944,
        0,
        1.889,
        0,
        2.833,
        0
      ]
    },
    {
      "Target": "Parameter",
      "Id": "empty9",
      "FadeInTime": -1.0,
      "FadeOutTime": -1.0,
      "Segments": [
        0,
        0,
        1,
        0.944,
        0,
        1.889,
        0,
        2.833,
        0
      ]
    },
    {
      "Target": "Parameter",
      "Id": "empty10",
      "FadeInTime": -1.0,
      "FadeOutTime": -1.0,
      "Segments": [
        0,
        0,
        1,
        0.944,
        0,
        1.889,
        0,
        2.833,
        0
      ]
    },
    {
      "Target": "Parameter",
      "Id": "empty11",
      "FadeInTime": -1.0,
      "FadeOutTime": -1.0,
      "Segments": [
        0,
        0,
        1,
        0.944,
        0,
        1.889,
        0,
        2.833,
        0
      ]
    },
    {
      "Target": "Parameter",
      "Id": "empty12",
      "FadeInTime": -1.0,
      "FadeOutTime": -1.0,
      "Segments": [
        0,
        0,
        1,
        0.944,
        0,
        1.889,
        0,
        2.833,
        0
      ]
    },
    {
      "Target": "Parameter",
      "Id": "empty13",
      "FadeInTime": -1.0,
      "FadeOutTime": -1.0,
      "Segments": [
        0,
        0,
        1,
        0.944,
        0,
        1.889,
        0,
        2.833,
        0
      ]
    },
    {
      "Target": "Parameter",
      "Id": "empty14",
      "FadeInTime": -1.0,
      "FadeOutTime": -1.0,
      "Segments": [
        0,
        0,
        1,
        0.944,
        0,
        1.889,
        0,
        2.833,
        0
      ]
    },
    {
      "Target": "Parameter",
      "Id": "empty15",
      "FadeInTime": -1.0,
      "FadeOutTime": -1.0,
      "Segments": [
        0,
        0,
        1,
        0.944,
        0,
        1.889,
        0,
        2.833,
        0
      ]
    },
    {
      "Target": "Parameter",
      "Id": "empty16",
      "FadeInTime": -1.0,
      "FadeOutTime": -1.0,
      "Segments": [
        0,
        0,
        1,
        0.944,
        0,
        1.889,
        0,
        2.833,
        0
      ]
    },
    {
      "Target": "Parameter",
      "Id": "empty17",
      "FadeInTime": -1.0,
      "FadeOutTime": -1.0,
      "Segments": [
        0,
        0,
        1,
        0.944,
        0,
        1.889,
        0,
        2.833,
        0
      ]
    },
    {
      "Target": "Parameter",
      "Id": "empty18",
      "FadeInTime": -1.0,
      "FadeOutTime": -1.0,
      "Segments": [
        0,
        0,
        1,
        0.944,
        0,
        1.889,
        0,
        2.833,
        0
      ]
    },
    {
      "Target": "Parameter",
      "Id": "empty19",
      "FadeInTime": -1.0,
      "FadeOutTime": -1.0,
      "Segments": [
        0,
        0,
        1,
        0.944,
        0,
        1.889,
        0,
        2.833,
        0
      ]
    },
    {
      "Target": "Parameter",
      "Id": "empty20",
      "FadeInTime": -1.0,
      "FadeOutTime": -1.0,
      "Segments": [
        0,
        0,
        1,
        0.944,
        0,
        1.889,
        0,
        2.833,
        0
      ]
    },
    {
      "Target": "Parameter",
      "Id": "empty21",
      "FadeInTime": -1.0,
      "FadeOutTime": -1.0,
      "Segments": [
        0,
        0,
        1,
        0.944,
        0,
        1.889,
        0,
        2.833,
        0
      ]
    },
    {
      "Target": "Parameter",
      "Id": "empty22",
      "FadeInTime": -1.0,
      "FadeOutTime": -1.0,
      "Segments": [
        0,
        0,
        1,
        0.944,
        0,
        1.889,
        0,
        2.833,
        0
      ]
    },
    {
      "Target": "Parameter",
      "Id": "empty23",
      "FadeInTime": -1.0,
      "FadeOutTime": -1.0,
      "Segments": [
        0,
        0,
        1,
        0.944,
        0,
        1.889,
        0,
        2.833,
        0
      ]
    },
    {
      "Target": "Parameter",
      "Id": "empty24",
      "FadeInTime": -1.0,
      "FadeOutTime": -1.0,
      "Segments": [
        0,
        0,
        1,
        0.944,
        0,
        1.889,
        0,
        2.833,
        0
      ]
    },
    {
      "Target": "Parameter",
      "Id": "empty25",
      "FadeInTime": -1.0,
      "FadeOutTime": -1.0,
      "Segments": [
        0,
        0,
        1,
        0.944,
        0,
        1.889,
        0,
        2.833,
        0
      ]
    },
    {
      "Target": "Parameter",
      "Id": "empty26",
      "FadeInTime": -1.0,
      "FadeOutTime": -1.0,
      "Segments": [
        0,
        0,
        1,
        0.944,
        0,
        1.889,
        0,
        2.833,
        0
      ]
    },
    {
      "Target": "Parameter",
      "Id": "empty27",
      "FadeInTime": -1.0,
      "FadeOutTime": -1.0,
      "Segments": [
        0,
        0,
        1,
        0.944,
        0,
        1.889,
        0,
        2.833,
        0
      ]
    },
    {
      "Target": "Parameter",
      "Id": "empty28",
      "FadeInTime": -1.0,
      "FadeOutTime": -1.0,
      "Segments": [
        0,
        0,
        1,
        0.944,
        0,
        1.889,
        0,
        2.833,
        0
      ]
    },
    {
      "Target": "Parameter",
      "Id": "empty29",
      "FadeInTime": -1.0,
      "FadeOutTime": -1.0,
      "Segments": [
        0,
        0,
        1,
        0.944,
        0,
        1.889,
        0,
        2.833,
        0
      ]
    },
    {
      "Target": "Parameter",
      "Id": "empty30",
      "FadeInTime": -1.0,
      "FadeOutTime": -1.0,
      "Segments": [
        0,
        0,
        1,
        0.944,
        0,
        1.889,
        0,
        2.833,
        0
      ]
    },
    {
      "Target": "Parameter",
      "Id": "empty31",
      "FadeInTime": -1.0,
      "FadeOutTime": -1.0,
      "Segments": [
        0,
        0,
        1,
        0.944,
        0,
        1.889,
        0,
        2.833,
        0
      ]
    },
    {
      "Target": "Parameter",
      "Id": "empty32",
      "FadeInTime": -1.0,
      "FadeOutTime": -1.0,
      "Segments": [
        0,
        0,
        1,
        0.944,
        0,
        1.889,
        0,
        2.833,
        0
      ]
    },
    {
      "Target": "Parameter",
      "Id": "empty33",
      "FadeInTime": -1.0,
      "FadeOutTime": -1.0,
      "Segments": [
        0,
        0,
        1,
        0.944,
        0,
        1.889,
        0,
        2.833,
        0
      ]
    },
    {
      "Target": "Parameter",
      "Id": "empty34",
      "FadeInTime": -1.0,
      "FadeOutTime": -1.0,
      "Segments": [
        0,
        0,
        1,
        0.944,
        0,
        1.889,
        0,
        2.833,
        0
      ]
    },
    {
      "Target": "Parameter",
      "Id": "empty35",
      "FadeInTime": -1.0,
      "FadeOutTime": -1.0,
      "Segments": [
        0,
        0,
        1,
        0.944,
        0,
        1.889,
        0,
        2.833,
        0
      ]
    },
    {
      "Target": "Parameter",
      "Id": "empty36",
      "FadeInTime": -1.0,
      "FadeOutTime": -1.0,
      "Segments": [
        0,
        0,
        1,
        0.944,
        0,
        1.889,
        0,
        2.833,
        0
      ]
    },
    {
      "Target": "Parameter",
      "Id": "empty37",
      "FadeInTime": -1.0,
      "FadeOutTime": -1.0,
      "Segments": [
        0,
        0,
        1,
        0.944,
        0,
        1.889,
        0,
        2.833,
        0
      ]
    },
    {
      "Target": "Parameter",
      "Id": "empty38",
      "FadeInTime": -1.0,
      "FadeOutTime": -1.0,
      "Segments": [
        0,
        0,
        1,
        0.944,
        0,
        1.889,
        0,
        2.833,
        0
      ]
    },
    {
      "Target": "Parameter",
      "Id": "empty39",
      "FadeInTime": -1.0,
      "FadeOutTime": -1.0,
      "Segments": [
        0,
        0,
        1,
        0.944,
        0,
        1.889,
        0,
        2.833,
        0
      ]
    },
    {
      "Target": "Parameter",
      "Id": "empty40",
      "FadeInTime": -1.0,
      "FadeOutTime": -1.0,
      "Segments": [
        0,
        0,
        1,
        0.944,
        0,
        1.889,
        0,
        2.833,
        0
      ]
    },
    {
      "Target": "Parameter",
      "Id": "empty41",
      "FadeInTime": -1.0,
      "FadeOutTime": -1.0,
      "Segments": [
        0,
        0,
        1,
        0.944,
        0,
        1.889,
        0,
        2.833,
        0
      ]
    },
    {
      "Target": "Parameter",
      "Id": "empty42",
      "FadeInTime": -1.0,
      "FadeOutTime": -1.0,
      "Segments": [
        0,
        0,
        1,
        0.944,
        0,
        1.889,
        0,
        2.833,
        0
      ]
    },
    {
      "Target": "Parameter",
      "Id": "empty43",
      "FadeInTime": -1.0,
      "FadeOutTime": -1.0,
      "Segments": [
        0,
        0,
        1,
        0.944,
        0,
        1.889,
        0,
        2.833,
        0
      ]
    },
    {
      "Target": "Parameter",
      "Id": "empty44",
      "FadeInTime": -1.0,
      "FadeOutTime": -1.0,
      "Segments": [
        0,
        0,
        1,
        0.944,
        0,
        1.889,
        0,
        2.833,
        0
      ]
    },
    {
      "Target": "Parameter",
      "Id": "empty45",
      "FadeInTime": -1.0,
      "FadeOutTime": -1.0,
      "Segments": [
        0,
        0,
        1,
        0.944,
        0,
        1.889,
        0,
        2.833,
        0
      ]
    },
    {
      "Target": "Parameter",
      "Id": "empty46",
      "FadeInTime": -1.0,
      "FadeOutTime": -1.0,
      "Segments": [
        0,
        0,
        1,
        0.944,
        0,
        1.889,
        0,
        2.833,
        0
      ]
    },
    {
      "Target": "Parameter",
      "Id": "empty47",
      "FadeInTime": -1.0,
      "FadeOutTime": -1.0,
      "Segments": [
        0,
        0,
        1,
        0.944,
        0,
        1.889,
        0,
        2.833,
        0
      ]
    },
    {
      "Target": "Parameter",
      "Id": "empty48",
      "FadeInTime": -1.0,
      "FadeOutTime": -1.0,
      "Segments": [
        0,
        0,
        1,
        0.944,
        0,
        1.889,
        0,
        2.833,
        0
      ]
    },
    {
      "Target": "Parameter",
      "Id": "empty49",
      "FadeInTime": -1.0,
      "FadeOutTime": -1.0,
      "Segments": [
        0,
        0,
        1,
        0.944,
        0,
        1.889,
        0,
        2.833,
        0
      ]
    },
    {
      "Target": "Parameter",
      "Id": "empty50",
      "FadeInTime": -1.0,
      "FadeOutTime": -1.0,
      "Segments": [
        0,
        0,
        1,
        0.944,
        0,
        1.889,
        0,
        2.833,
        0
      ]
    },
    {
      "Target": "Parameter",
      "Id": "empty51",
      "FadeInTime": -1.0,
      "FadeOutTime": -1.0,
      "Segments": [
        0,
        0,
        1,
        0.944,
        0,
        1.889,
        0,
        2.833,
        0
      ]
    },
    {
      "Target": "Parameter",
      "Id": "empty52",
      "FadeInTime": -1.0,
      "FadeOutTime": -1.0,
      "Segments": [
        0,
        0,
        1,
        0.944,
        0,
        1.889,
        0,
        2.833,
        0
      ]
    },
    {
      "Target": "Parameter",
      "Id": "empty53",
      "FadeInTime": -1.0,
      "FadeOutTime": -1.0,
      "Segments": [
        0,
        0,
        1,
        0.944,
        0,
        1.889,
        0,
        2.833,
        0
      ]
    },
    {
      "Target": "Parameter",
      "Id": "empty54",
      "FadeInTime": -1.0,
      "FadeOutTime": -1.0,
      "Segments": [
        0,
        0,
        1,
        0.944,
        0,
        1.889,
        0,
        2.833,
        0
      ]
    },
    {
      "Target": "Parameter",
      "Id": "empty55",
      "FadeInTime": -1.0,
      "FadeOutTime": -1.0,
      "Segments": [
        0,
        0,
        1,
        0.944,
        0,
        1.889,
        0,
        2.833,
        0
      ]
    },
    {
      "Target": "Parameter",
      "Id": "empty56",
      "FadeInTime": -1.0,
      "FadeOutTime": -1.0,
      "Segments": [
        0,
        0,
        1,
        0.944,
        0,
        1.889,
        0,
        2.833,
        0
      ]
    },
    {
      "Target": "Parameter",
      "Id": "empty57",
      "FadeInTime": -1.0,
      "FadeOutTime": -1.0,
      "Segments": [
        0,
        0,
        1,
        0.944,
        0,
        1.889,
        0,
        2.833,
        0
      ]
    },
    {
      "Target": "Parameter",
      "Id": "empty58",
      "FadeInTime": -1.0,
      "FadeOutTime": -1.0,
      "Segments": [
        0,
        0,
        1,
        0.944,
        0,
        1.889,
        0,
        2.833,
        0
      ]
    },
    {
      "Target": "Parameter",
      "Id": "empty59",
      "FadeInTime": -1.0,
      "FadeOutTime": -1.0,
      "Segments": [
        0,
        0,
        1,
        0.944,
        0,
        1.889,
        0,
        2.833,
        0
      ]
    },
    {
      "Target": "Parameter",
      "Id": "empty60",
      "FadeInTime": -1.0,
      "FadeOutTime": -1.0,
      "Segments": [
        0,
        0,
        1,
        0.944,
        0,
        1.889,
        0,
        2.833,
        0
      ]
    }
  ],
  "UserData": [
    {
      "Time": 2.333,
      "Value": ""
    }
  ]
}